[
  {
    "Lat": 55.69076,
    "Lon": 37.500362,
    "Id": "920b3d67-3469-4c6d-9997-cd88ec370d98",
    "Number": 1,
    "Cells": {
      "name":
        "Государственное бюджетное образовательное учреждение города Москвы  центр образования № 1434",
      "adress": "119607 г.Москва, ул Раменки д.15 к1",
      "okryg": "Западный административный округ",
      "rayon": "район Раменки",
      "org_prav_forma": "Государственное",
      "podchinenie": "Западное окружное управление образования",
      "tip_ychregdenia": "Общеобразовательное учреждение",
      "vid_ychregdenia": "Центр образования",
      "telefon": "(495) 932-00-00; (495) 932-08-01",
      "sait": "co1434.mskzapad.ru",
      "email": "coe1434@mail.ru",
      "X": "37,500362",
      "Y": "55,69076",
      "global_id": "86660709"
    }
  },
  {
    "Lat": 55.735511,
    "Lon": 37.491154,
    "Id": "565f1062-6c5a-47e2-bbda-c828d52b6a99",
    "Number": 2,
    "Cells": {
      "name":
        "Государственное бюджетное образовательное учреждение города Москвы центр образования № 1816",
      "adress": "121096 г. Москва, ул. Кастанаевская, д. 9А",
      "okryg": "Западный административный округ",
      "rayon": "район Филёвский Парк",
      "org_prav_forma": "Государственное",
      "podchinenie": "Западное окружное управление образования",
      "tip_ychregdenia": "Общеобразовательное учреждение",
      "vid_ychregdenia": "Центр образования",
      "telefon": "(499) 144-37-82",
      "sait": "co1816.mskzapad.ru",
      "email": "gou1816@rambler.ru",
      "X": "37,491154",
      "Y": "55,735511",
      "global_id": "86660727"
    }
  },
  {
    "Lat": 55.578072,
    "Lon": 37.657325,
    "Id": "5de814e2-4db6-4e18-a468-5345d64266cf",
    "Number": 3,
    "Cells": {
      "name":
        "Частное учреждение \"Православный центр образования Святителя Николая Чудотворца\"",
      "adress": "117403 г. Москва, Булатниковский пр., д. 16, к. 3",
      "okryg": "Южный административный округ",
      "rayon": "район Бирюлёво Западное",
      "org_prav_forma": "Негосударственное",
      "podchinenie": "Негосударственное",
      "tip_ychregdenia": "Общеобразовательное учреждение",
      "vid_ychregdenia": "Центр образования",
      "telefon": "(495) 383-89-56",
      "sait": "noupcosnch.mskobr.ru",
      "email": "revdimitri@inbox.ru",
      "X": "37,657325",
      "Y": "55,578072",
      "global_id": "86887462"
    }
  },
  {
    "Lat": 55.623761,
    "Lon": 37.702347,
    "Id": "7ac90081-5185-4dcc-86b1-f51b891a501a",
    "Number": 4,
    "Cells": {
      "name":
        "Государственное автономное образовательное учреждение города Москвы центр образования № 548 \"Царицыно\"",
      "adress": "115582 г.Москва, ул. Домодедовская д35, к.2",
      "okryg": "Южный административный округ",
      "rayon": "район Орехово-Борисово Северное",
      "org_prav_forma": "Государственное",
      "podchinenie": "Южное окружное управление образования",
      "tip_ychregdenia": "Общеобразовательное учреждение",
      "vid_ychregdenia": "Центр образования",
      "telefon": "393-43-81",
      "sait": "cou548.mskobr.ru",
      "email": "sch548@sinergi.ru",
      "X": "37,702347",
      "Y": "55,623761",
      "global_id": "86887505"
    }
  },
  {
    "Lat": 55.620614,
    "Lon": 37.754942,
    "Id": "50c38544-d9ef-444c-8b55-250163210713",
    "Number": 5,
    "Cells": {
      "name":
        "Государственное бюджетное образовательное учреждение города Москвы центр образования № 936",
      "adress": "115682 г. Москва, Задонский пр. д.34,к.3",
      "okryg": "Южный административный округ",
      "rayon": "район Зябликово",
      "org_prav_forma": "Государственное",
      "podchinenie": "Южное окружное управление образования",
      "tip_ychregdenia": "Общеобразовательное учреждение",
      "vid_ychregdenia": "Центр образования",
      "telefon": "395-92-64",
      "sait": "cou936.mskobr.ru",
      "email": "sch936@sinergi.ru",
      "X": "37,754942",
      "Y": "55,620614",
      "global_id": "86887538"
    }
  },
  {
    "Lat": 55.639744,
    "Lon": 37.774136,
    "Id": "7396109b-34fa-45e2-b3bb-e7aa538b1ac3",
    "Number": 6,
    "Cells": {
      "name":
        "Государственное бюджетное образовательное учреждение города Москвы центр образования № 975",
      "adress": "115408 Москва, ул. Алма-Атиинская д.9,к.3",
      "okryg": "Южный административный округ",
      "rayon": "район Братеево",
      "org_prav_forma": "Государственное",
      "podchinenie": "Южное окружное управление образования",
      "tip_ychregdenia": "Общеобразовательное учреждение",
      "vid_ychregdenia": "Центр образования",
      "telefon": "341-86-83",
      "sait": "cou975.mskobr.ru",
      "email": "sch975@sinergi.ru",
      "X": "37,774136",
      "Y": "55,639744",
      "global_id": "86887544"
    }
  },
  {
    "Lat": 55.646502,
    "Lon": 37.614265,
    "Id": "8d8e44a0-c096-4fb9-b6e6-d1ee8ca68936",
    "Number": 7,
    "Cells": {
      "name":
        "Государственное бюджетное образовательное учреждение города Москвы центр образования № 1862",
      "adress": "117452 г. Москва, ул. Черноморский бульвар д.6",
      "okryg": "Южный административный округ",
      "rayon": "Нагорный район",
      "org_prav_forma": "Государственное",
      "podchinenie": "Южное окружное управление образования",
      "tip_ychregdenia": "Общеобразовательное учреждение",
      "vid_ychregdenia": "Центр образования",
      "telefon": "(499) 610-77-66",
      "sait": "cou1862.mskobr.ru",
      "email": "sch1862@sinergi.ru",
      "X": "37,614265",
      "Y": "55,646502",
      "global_id": "86887580"
    }
  },
  {
    "Lat": 55.893846,
    "Lon": 37.575491,
    "Id": "828088bb-d469-487c-b8ff-dc489ec03686",
    "Number": 8,
    "Cells": {
      "name":
        "Автономная некоммерческая организация Центр образования \"Знак\"",
      "adress": "127576 Москва ул. Абрамцевская д.6а",
      "okryg": "Северо-Восточный административный округ",
      "rayon": "район Лианозово",
      "org_prav_forma": "Негосударственное",
      "podchinenie": "Негосударственное",
      "tip_ychregdenia": "Общеобразовательное учреждение",
      "vid_ychregdenia": "Центр образования",
      "telefon": "(499) 200-05-08",
      "sait": "nouznak.mskobr.ru",
      "email": "lic@bk.ru",
      "X": "37,575491",
      "Y": "55,893846",
      "global_id": "86887613"
    }
  },
  {
    "Lat": 55.616705,
    "Lon": 37.588365,
    "Id": "cb510c07-9460-4f3b-819a-58510fabf0d3",
    "Number": 9,
    "Cells": {
      "name":
        "Некоммерческое партнерство Центр образования Лицей \"Столичный\"",
      "adress":
        "115470, г. Москва, ул. Кленовый бульвар, д.6, корпус 2, строение 1",
      "okryg": "Южный административный округ",
      "rayon": "район Чертаново Центральное",
      "org_prav_forma": "Негосударственное",
      "podchinenie": "Негосударственное",
      "tip_ychregdenia": "Общеобразовательное учреждение",
      "vid_ychregdenia": "Центр образования",
      "telefon": "(495) 313-49-79,(495) 315-31-56",
      "sait": "noustolichnyj.mskobr.ru",
      "email": "lycee@lstol.ru",
      "X": "37,588365",
      "Y": "55,616705",
      "global_id": "86887615"
    }
  },
  {
    "Lat": 55.719402,
    "Lon": 37.789439,
    "Id": "0c1db036-7156-46a8-b481-f7d3477a6ea5",
    "Number": 10,
    "Cells": {
      "name": "Частное учреждение Центр образования \"Личность\"",
      "adress": null,
      "okryg": "Юго-Восточный административный округ",
      "rayon": "Рязанский район",
      "org_prav_forma": "Негосударственное",
      "podchinenie": "Негосударственное",
      "tip_ychregdenia": "Общеобразовательное учреждение",
      "vid_ychregdenia": "Центр образования",
      "telefon": "(495) 371-55-92,(495) 371-59-00,(495) 643-89-60",
      "sait": "noulichnost.mskobr.ru",
      "email": "info@school-lichnost.ru",
      "X": "37,789439",
      "Y": "55,719402",
      "global_id": "86887628"
    }
  },
  {
    "Lat": 55.662815,
    "Lon": 37.558987,
    "Id": "13677a3f-7e4e-4e7b-8bbc-e0735fbfb751",
    "Number": 11,
    "Cells": {
      "name":
        "Негосударственное образовательное учреждение Средняя общеобразовательная школа Образовательный центр ОАО \"Газпром\"",
      "adress": null,
      "okryg": "Юго-Западный административный округ",
      "rayon": "район Черёмушки",
      "org_prav_forma": "Негосударственное",
      "podchinenie": "Негосударственное",
      "tip_ychregdenia": "Общеобразовательное учреждение",
      "vid_ychregdenia": "Центр образования",
      "telefon": "(495) 719-17-10",
      "sait": "nougazprom.mskobr.ru",
      "email": "ocgaz@mail.ru",
      "X": "37,558987",
      "Y": "55,662815",
      "global_id": "86887640"
    }
  },
  {
    "Lat": 55.75925,
    "Lon": 37.806119,
    "Id": "3f7a13bb-6de6-4c75-820e-3b11a27bd707",
    "Number": 12,
    "Cells": {
      "name":
        "Автономная некоммерческая организация образовательный центр \"ЭОС\"",
      "adress": null,
      "okryg": "Восточный административный округ",
      "rayon": "район Ивановское",
      "org_prav_forma": "Негосударственное",
      "podchinenie": "Негосударственное",
      "tip_ychregdenia": "Общеобразовательное учреждение",
      "vid_ychregdenia": "Центр образования",
      "telefon": "305-77-22,304-73-86",
      "sait": "noueos.mskobr.ru",
      "email": "eos-center@yandex.ru",
      "X": "37,806119",
      "Y": "55,75925",
      "global_id": "86887648"
    }
  },
  {
    "Lat": 55.807493,
    "Lon": 37.722008,
    "Id": "b9e40515-b1d4-481d-82f1-0ee05d677996",
    "Number": 13,
    "Cells": {
      "name": "Частное учреждение Центр образования \"Школа Ретро\"",
      "adress": "107370 Москва 4-я Гражданская ул., д.43, к.8",
      "okryg": "Восточный административный округ",
      "rayon": "район Богородское",
      "org_prav_forma": "Негосударственное",
      "podchinenie": "Негосударственное",
      "tip_ychregdenia": "Общеобразовательное учреждение",
      "vid_ychregdenia": "Центр образования",
      "telefon": "(499) 160-86-25,(495) 646-95-94",
      "sait": null,
      "email": "retro@retro-school.com",
      "X": "37,722008",
      "Y": "55,807493",
      "global_id": "86887649"
    }
  },
  {
    "Lat": 55.715802,
    "Lon": 37.440425,
    "Id": "e2d9987c-208f-47ec-b647-3e38c03bb1bf",
    "Number": 14,
    "Cells": {
      "name": "Некоммерческое образовательное учреждение \"Центр ЮССТ\"",
      "adress": null,
      "okryg": "Западный административный округ",
      "rayon": "Можайский район",
      "org_prav_forma": "Негосударственное",
      "podchinenie": "Негосударственное",
      "tip_ychregdenia": "Общеобразовательное учреждение",
      "vid_ychregdenia": "Центр образования",
      "telefon": "446-34-78,(495) 970-06-89",
      "sait": null,
      "email": "info@usst.ru",
      "X": "37,440425",
      "Y": "55,715802",
      "global_id": "86887666"
    }
  },
  {
    "Lat": 55.710975,
    "Lon": 37.757253,
    "Id": "9f29a58a-3da5-4905-8126-4ad8d085b199",
    "Number": 15,
    "Cells": {
      "name":
        "Государственное бюджетное образовательное учреждение города Москвы центр образования № 825",
      "adress": "109125, г. Москва, ул. Окская, д. 16, корп. 3",
      "okryg": "Юго-Восточный административный округ",
      "rayon": "район Кузьминки",
      "org_prav_forma": "Государственное",
      "podchinenie": "Юго-Восточное окружное управление образования",
      "tip_ychregdenia": "Общеобразовательное учреждение",
      "vid_ychregdenia": "Центр образования",
      "telefon": "(499) 177-62-77",
      "sait": "cog825.mskobr.ru",
      "email": "sch_825@gor.educom.ru",
      "X": "37,757253",
      "Y": "55,710975",
      "global_id": "86887669"
    }
  },
  {
    "Lat": 55.668921,
    "Lon": 37.464914,
    "Id": "3aaf1272-2195-4535-a8be-218f35636ff8",
    "Number": 16,
    "Cells": {
      "name":
        "Государственное бюджетное образовательное учреждение города Москвы центр образования № 1329",
      "adress": "119602, г. Москва, ул. Никулинская, д.10",
      "okryg": "Западный административный округ",
      "rayon": "район Тропарёво-Никулино",
      "org_prav_forma": "Государственное",
      "podchinenie": "Западное окружное управление образования",
      "tip_ychregdenia": "Общеобразовательное учреждение",
      "vid_ychregdenia": "Центр образования",
      "telefon": "651-33-97",
      "sait": "co1329.mskzapad.ru/",
      "email": "info@sch1329.ru",
      "X": "37,464914",
      "Y": "55,668921",
      "global_id": "86887711"
    }
  },
  {
    "Lat": 55.632324,
    "Lon": 37.476879,
    "Id": "c179c449-9059-4b68-b6af-c33a29fe9e93",
    "Number": 17,
    "Cells": {
      "name":
        "Негосударственное образовательное учреждение образовательный центр \"Солнечный ветер\"",
      "adress": null,
      "okryg": "Юго-Западный административный округ",
      "rayon": "район Тёплый Стан",
      "org_prav_forma": "Негосударственное",
      "podchinenie": "Негосударственное",
      "tip_ychregdenia": "Общеобразовательное учреждение",
      "vid_ychregdenia": "Центр образования",
      "telefon": "500-82-59,338-25-55",
      "sait": null,
      "email": "sunnywind@mtu-net.ru",
      "X": "37,476879",
      "Y": "55,632324",
      "global_id": "86887725"
    }
  },
  {
    "Lat": 55.61952,
    "Lon": 37.735904,
    "Id": "b35de634-fa23-41c6-8d80-8cfd4e81f393",
    "Number": 18,
    "Cells": {
      "name":
        "Государственное бюджетное образовательное учреждение города Москвы центр образования № 1433",
      "adress": "115573 г. Москва, Шипиловская, ул., д.46 корп.3",
      "okryg": "Южный административный округ",
      "rayon": "район Зябликово",
      "org_prav_forma": "Государственное",
      "podchinenie": "Южное окружное управление образования",
      "tip_ychregdenia": "Общеобразовательное учреждение",
      "vid_ychregdenia": "Центр образования",
      "telefon": "(495) 390-02-28; (495) 390-34-50; (495) 393-01-02",
      "sait": "cou1433.mskobr.ru/",
      "email": "sch1433@sinergi.ru",
      "X": "37,735904",
      "Y": "55,61952",
      "global_id": "86887746"
    }
  },
  {
    "Lat": 55.578116,
    "Lon": 37.680195,
    "Id": "9af6fa9e-b0ce-403a-a08c-3bd3cc27c7c6",
    "Number": 19,
    "Cells": {
      "name":
        "Государственное бюджетное образовательное учреждение города Москвы центр образования № 1861 \"Загорье\"",
      "adress": "115598 Москва, Загорьевский пр., 13",
      "okryg": "Южный административный округ",
      "rayon": "район Бирюлёво Восточное",
      "org_prav_forma": "Государственное",
      "podchinenie": "Южное окружное управление образования",
      "tip_ychregdenia": "Общеобразовательное учреждение",
      "vid_ychregdenia": "Центр образования",
      "telefon": "392-71-22",
      "sait": "cou1861.mskobr.ru",
      "email": "sch1861@sinergi.ru",
      "X": "37,680195",
      "Y": "55,578116",
      "global_id": "86887747"
    }
  },
  {
    "Lat": 55.757531,
    "Lon": 37.412665,
    "Id": "80548156-55c7-4064-8552-264c72813980",
    "Number": 20,
    "Cells": {
      "name":
        "Государственное бюджетное образовательное учреждение города Москвы центр образования № 1440",
      "adress": "121609 г.Москва, Осенний бульвар, д. 10, корпус 3",
      "okryg": "Западный административный округ",
      "rayon": "район Крылатское",
      "org_prav_forma": "Государственное",
      "podchinenie": "Западное окружное управление образования",
      "tip_ychregdenia": "Общеобразовательное учреждение",
      "vid_ychregdenia": "Центр образования",
      "telefon": "415-98-55",
      "sait": "co1440.mskzapad.ru",
      "email": "sch1304@inbox.ru",
      "X": "37,412665",
      "Y": "55,757531",
      "global_id": "86887751"
    }
  },
  {
    "Lat": 55.642621,
    "Lon": 37.341367,
    "Id": "95eb21c9-f85f-4789-847a-89a2d60db36f",
    "Number": 21,
    "Cells": {
      "name":
        "Государственное бюджетное образовательное учреждение города Москвы центр образования № 1432 \"Новая школа\"",
      "adress": "119634 г.Москва, ул.Шолохова, д. 19",
      "okryg": "Западный административный округ",
      "rayon": "район Ново-Переделкино",
      "org_prav_forma": "Государственное",
      "podchinenie": "Западное окружное управление образования",
      "tip_ychregdenia": "Общеобразовательное учреждение",
      "vid_ychregdenia": "Центр образования",
      "telefon": "732-74-60",
      "sait": "co1432.mskzapad.ru",
      "email": "sch1019@mail.ru",
      "X": "37,341367",
      "Y": "55,642621",
      "global_id": "86887754"
    }
  },
  {
    "Lat": 55.650978,
    "Lon": 37.366901,
    "Id": "8df3e6cc-b39d-407d-8d4e-47534b5e2ba2",
    "Number": 22,
    "Cells": {
      "name":
        "Государственное бюджетное образовательное учреждение города Москвы центр образования № 1455",
      "adress": "119633 г.Москва, Боровское шоссе, д.18, корп.4",
      "okryg": "Западный административный округ",
      "rayon": "район Ново-Переделкино",
      "org_prav_forma": "Государственное",
      "podchinenie": "Западное окружное управление образования",
      "tip_ychregdenia": "Общеобразовательное учреждение",
      "vid_ychregdenia": "Центр образования",
      "telefon": "732-13-50",
      "sait": "co1455.mskzapad.ru",
      "email": "sch2002adm@mail.ru",
      "X": "37,366901",
      "Y": "55,650978",
      "global_id": "86887757"
    }
  },
  {
    "Lat": 55.63428,
    "Lon": 37.380609,
    "Id": "ff01c2e4-9229-481e-a41f-76e5fd4fa4e8",
    "Number": 23,
    "Cells": {
      "name":
        "Государственное бюджетное образовательное учреждение города Москвы центр образования № 1436",
      "adress": "119297 г.Москва, ул. Родниковая, д.20, корпус 1",
      "okryg": "Западный административный округ",
      "rayon": "район Солнцево",
      "org_prav_forma": "Государственное",
      "podchinenie": "Западное окружное управление образования",
      "tip_ychregdenia": "Общеобразовательное учреждение",
      "vid_ychregdenia": "Центр образования",
      "telefon": "934-76-20",
      "sait": "co1436.mskzapad.ru",
      "email": "ce1436@mail.ru",
      "X": "37,380609",
      "Y": "55,63428",
      "global_id": "86887770"
    }
  },
  {
    "Lat": 55.639877,
    "Lon": 37.336993,
    "Id": "4268683d-eec3-4c9a-8b1a-d0d6de6e51ee",
    "Number": 24,
    "Cells": {
      "name":
        "Государственное бюджетное образовательное учреждение города Москвы Центр образования № 1437",
      "adress": "119634 г. Москва, ул. Федосьино, д.16, корп.3",
      "okryg": "Западный административный округ",
      "rayon": "район Ново-Переделкино",
      "org_prav_forma": "Государственное",
      "podchinenie": "Западное окружное управление образования",
      "tip_ychregdenia": "Общеобразовательное учреждение",
      "vid_ychregdenia": "Центр образования",
      "telefon": "731-10-55",
      "sait": "co1437.mskzapad.ru",
      "email": "co_1437@mail.ru",
      "X": "37,336993",
      "Y": "55,639877",
      "global_id": "86887771"
    }
  },
  {
    "Lat": 55.599126,
    "Lon": 37.513574,
    "Id": "2787f383-d7c8-4f5f-af10-a2673785a28a",
    "Number": 25,
    "Cells": {
      "name":
        "Негосударственное образовательное учреждение центр образования \"Православная классическая гимназия \"Радонеж\"",
      "adress": null,
      "okryg": "Юго-Западный административный округ",
      "rayon": "район Ясенево",
      "org_prav_forma": "Государственное",
      "podchinenie": "Негосударственное",
      "tip_ychregdenia": "Общеобразовательное учреждение",
      "vid_ychregdenia": "Центр образования",
      "telefon": "(495) 423-51-22",
      "sait": null,
      "email": "info@gymnasia-radonezh.ru",
      "X": "37,513574",
      "Y": "55,599126",
      "global_id": "86887799"
    }
  },
  {
    "Lat": 55.606526,
    "Lon": 37.73876,
    "Id": "afec2785-afec-4ff5-8903-2ea9d428c2da",
    "Number": 26,
    "Cells": {
      "name":
        "Негосударственное образовательное учреждение центр образования «Православный Центр непрерывного образования во имя преподобного Серафима Саровского»",
      "adress": "115597, Москва, ул. Ясеневая д.33 корп.2",
      "okryg": "Южный административный округ",
      "rayon": "район Орехово-Борисово Южное",
      "org_prav_forma": "Негосударственное",
      "podchinenie": "Негосударственное",
      "tip_ychregdenia": "Общеобразовательное учреждение",
      "vid_ychregdenia": "Центр образования",
      "telefon": "(495) 548-24-12,(495) 399-44-79",
      "sait": null,
      "email": "pravoslavnycentr@inbox.ru",
      "X": "37,73876",
      "Y": "55,606526",
      "global_id": "86890207"
    }
  },
  {
    "Lat": 55.616955,
    "Lon": 37.681485,
    "Id": "1382e2c5-a95c-4a43-8ea7-d116c5ff0bd4",
    "Number": 27,
    "Cells": {
      "name": "Частное учреждение Центр образования «Русская школа»",
      "adress": "115569,г.Москва ,ул.Дольская,д.2",
      "okryg": "Южный административный округ",
      "rayon": "район Орехово-Борисово Северное",
      "org_prav_forma": "Негосударственное",
      "podchinenie": "Негосударственное",
      "tip_ychregdenia": "Общеобразовательное учреждение",
      "vid_ychregdenia": "Центр образования",
      "telefon": "548-07-55",
      "sait": null,
      "email": null,
      "X": "37,681485",
      "Y": "55,616955",
      "global_id": "86890209"
    }
  },
  {
    "Lat": 55.717683,
    "Lon": 37.614535,
    "Id": "9bf970be-ee11-431b-8976-09e10fcd5f12",
    "Number": 28,
    "Cells": {
      "name": "Частное учреждение Центр Образования \"Столичный - КИТ\"",
      "adress": "115162, Москва, Хавская ул., д.5",
      "okryg": "Южный административный округ",
      "rayon": "Даниловский район",
      "org_prav_forma": "Негосударственное",
      "podchinenie": "Негосударственное",
      "tip_ychregdenia": "Общеобразовательное учреждение",
      "vid_ychregdenia": "Центр образования",
      "telefon": "(499) 764-74-87",
      "sait": "noustolichnkit.mskobr.ru",
      "email": "s-kit@bk.ru",
      "X": "37,614535",
      "Y": "55,717683",
      "global_id": "86890219"
    }
  },
  {
    "Lat": 55.702474,
    "Lon": 37.512648,
    "Id": "9145533f-efdb-4d36-b937-7701fbe7d4ca",
    "Number": 29,
    "Cells": {
      "name":
        "Государственное бюджетное образовательное учреждение города Москвы Центр образования № 1448",
      "adress": "119192 г.Москва, Мичуринский проспект, д. 5, корпус 1",
      "okryg": "Западный административный округ",
      "rayon": "район Раменки",
      "org_prav_forma": "Государственное",
      "podchinenie": "Западное окружное управление образования",
      "tip_ychregdenia": "Общеобразовательное учреждение",
      "vid_ychregdenia": "Центр образования",
      "telefon": "(495) 641-16-27",
      "sait": null,
      "email": "school1448@mail.ru",
      "X": "37,512648",
      "Y": "55,702474",
      "global_id": "86890227"
    }
  },
  {
    "Lat": 55.653386,
    "Lon": 37.483574,
    "Id": "87032a0c-8849-4f72-9af4-643584c4d31e",
    "Number": 30,
    "Cells": {
      "name":
        "Государственное бюджетное образовательное учреждение города Москвы центр образования № 1485",
      "adress": "119571 г.Москва, Проспект Вернадского, д. 127, корпус 2",
      "okryg": "Западный административный округ",
      "rayon": "район Тропарёво-Никулино",
      "org_prav_forma": "Государственное",
      "podchinenie": "Западное окружное управление образования",
      "tip_ychregdenia": "Общеобразовательное учреждение",
      "vid_ychregdenia": "Центр образования",
      "telefon":
        "(495) 438-75-44; (495) 438-75-56; (495) 438-75-88; (495) 438-71-65; (495) 438-65-56; (495) 438-75-66; (495) 438-55-65; (495) 438-61-92",
      "sait": "co1485.mskzapad.ru",
      "email": "school1485@mail.ru",
      "X": "37,483574",
      "Y": "55,653386",
      "global_id": "86890229"
    }
  },
  {
    "Lat": 55.613076,
    "Lon": 37.288846,
    "Id": "33757659-95b8-4c29-ba38-265b447bd6c7",
    "Number": 31,
    "Cells": {
      "name":
        "Государственное бюджетное образовательное учреждение города Москвы центр образования № 1473 имени Григория Алексеевича Тарана",
      "adress": "119027 г.Москва, пос. Внуково, ул. Центральная, д. 15 А",
      "okryg": "Западный административный округ",
      "rayon": "район Внуково",
      "org_prav_forma": "Государственное",
      "podchinenie": "Западное окружное управление образования",
      "tip_ychregdenia": "Общеобразовательное учреждение",
      "vid_ychregdenia": "Центр образования",
      "telefon": "(495) 436-84-07; (495) 436-82-27; (495) 436-28-07",
      "sait": "co1473.mskzapad.ru",
      "email": "sch1473@bk.ru",
      "X": "37,288846",
      "Y": "55,613076",
      "global_id": "86890232"
    }
  },
  {
    "Lat": 55.770761,
    "Lon": 37.4136,
    "Id": "bf6bbe87-f6af-4d60-8149-a591b4ff4b24",
    "Number": 32,
    "Cells": {
      "name":
        "Государственное бюджетное образовательное учреждение города Москвы центр образования № 1471",
      "adress": "121614 г. Москва, ул. Крылатская, д.25",
      "okryg": "Западный административный округ",
      "rayon": "район Крылатское",
      "org_prav_forma": "Государственное",
      "podchinenie": "Западное окружное управление образования",
      "tip_ychregdenia": "Общеобразовательное учреждение",
      "vid_ychregdenia": "Центр образования",
      "telefon": "413-33-32",
      "sait": null,
      "email": "1471ec@gmail.com",
      "X": "37,4136",
      "Y": "55,770761",
      "global_id": "86890242"
    }
  },
  {
    "Lat": 55.742785,
    "Lon": 37.680907,
    "Id": "0de2a0fd-bf84-4746-95da-3794bb9ea845",
    "Number": 33,
    "Cells": {
      "name":
        "Государственное бюджетное образовательное учреждение города Москвы центр образования № 1468",
      "adress": "109544 г.Москва, Новорогожская ул., д.9.",
      "okryg": "Центральный административный округ",
      "rayon": "Таганский район",
      "org_prav_forma": "Государственное",
      "podchinenie": "Центральное окружное управление образования",
      "tip_ychregdenia": "Общеобразовательное учреждение",
      "vid_ychregdenia": "Центр образования",
      "telefon": "(495) 678-73-78; (495) 678-74-71",
      "sait": "coc1468.mskobr.ru",
      "email": "tsentr1468@mail.ru",
      "X": "37,680907",
      "Y": "55,742785",
      "global_id": "86890261"
    }
  },
  {
    "Lat": 55.639118,
    "Lon": 37.347582,
    "Id": "3e1b5855-f5a4-493e-98f1-81ade80a358d",
    "Number": 34,
    "Cells": {
      "name":
        "Государственное бюджетное образовательное учреждение города Москвы центр образования № 1467",
      "adress": "119634 г.Москва, ул.Шолохова, д. 9",
      "okryg": "Западный административный округ",
      "rayon": "район Ново-Переделкино",
      "org_prav_forma": "Государственное",
      "podchinenie": "Западное окружное управление образования",
      "tip_ychregdenia": "Общеобразовательное учреждение",
      "vid_ychregdenia": "Центр образования",
      "telefon": "733-53-42",
      "sait": "co1467.mskzapad.ru",
      "email": "sch1006@yandex.ru",
      "X": "37,347582",
      "Y": "55,639118",
      "global_id": "86890269"
    }
  },
  {
    "Lat": 55.846581,
    "Lon": 37.34348,
    "Id": "a3a45df6-cfd6-4356-8d0a-c5192044bb7c",
    "Number": 35,
    "Cells": {
      "name":
        "Государственное бюджетное образовательное учреждение города Москвы Центр образования № 1463",
      "adress": "123368, г.Москва, ул.Барышиха, д.29, к.1",
      "okryg": "Северо-Западный административный округ",
      "rayon": "район Митино",
      "org_prav_forma": "Государственное",
      "podchinenie": "Северо-Западное окружное управление образования",
      "tip_ychregdenia": "Общеобразовательное учреждение",
      "vid_ychregdenia": "Центр образования",
      "telefon": "754-14-61",
      "sait": "co1463.mskobr.ru/",
      "email": " sch1463@szouo.ru",
      "X": "37,34348",
      "Y": "55,846581",
      "global_id": "86890272"
    }
  },
  {
    "Lat": 55.691562,
    "Lon": 37.851274,
    "Id": "3a351d62-4171-4549-8323-e5f13f03ff4d",
    "Number": 36,
    "Cells": {
      "name":
        "Государственное бюджетное образовательное учреждение города Москвы центр образования № 1460",
      "adress": "109156, г. Москва, ул. Привольная, д. 37",
      "okryg": "Юго-Восточный административный округ",
      "rayon": "район Выхино-Жулебино",
      "org_prav_forma": "Государственное",
      "podchinenie": "Юго-Восточное окружное управление образования",
      "tip_ychregdenia": "Общеобразовательное учреждение",
      "vid_ychregdenia": "Центр образования",
      "telefon": "(495) 704-52-10; (495) 704-56-01; (495) 704-53-11",
      "sait": "co1460uv.mskobr.ru",
      "email": "school1907@mail.ru",
      "X": "37,851274",
      "Y": "55,691562",
      "global_id": "86890276"
    }
  },
  {
    "Lat": 55.81428,
    "Lon": 37.567834,
    "Id": "707b6840-50cb-4f93-b953-187383d3a4d0",
    "Number": 37,
    "Cells": {
      "name":
        "Государственное бюджетное образовательное учреждение города Москвы центр образования № 1454",
      "adress": "127422,  г. Москва, улица Тимирязевская, дом 14 \"А\"",
      "okryg": "Северный административный округ",
      "rayon": "Тимирязевский район",
      "org_prav_forma": "Государственное",
      "podchinenie": "Северное окружное управление образования",
      "tip_ychregdenia": "Общеобразовательное учреждение",
      "vid_ychregdenia": "Центр образования",
      "telefon": "(495) 611-15-38",
      "sait": "schs1454.mskobr.ru/",
      "email": "co1454@mail.ru",
      "X": "37,567834",
      "Y": "55,81428",
      "global_id": "86890279"
    }
  },
  {
    "Lat": 55.777024,
    "Lon": 37.831504,
    "Id": "088ae487-b4ff-49dc-accc-ea018b7d7a76",
    "Number": 38,
    "Cells": {
      "name":
        "Государственное бюджетное образовательное учреждение города Москвы центр образования № 1476",
      "adress": "105568, Москва, ул. Челябинская, д. 20",
      "okryg": "Восточный административный округ",
      "rayon": "район Ивановское",
      "org_prav_forma": "Государственное",
      "podchinenie": "Восточное окружное управление образования",
      "tip_ychregdenia": "Общеобразовательное учреждение",
      "vid_ychregdenia": "Центр образования",
      "telefon": "308-00-29",
      "sait": "cov1476.mskobr.ru",
      "email": "shkla350@rambler.ru",
      "X": "37,831504",
      "Y": "55,777024",
      "global_id": "86890282"
    }
  },
  {
    "Lat": 55.790653,
    "Lon": 37.793722,
    "Id": "ea9e80db-b0ad-4dcd-9f33-6d3b666aa268",
    "Number": 39,
    "Cells": {
      "name":
        "Государственное бюджетное образовательное учреждение города Москвы Центр образования № 1483",
      "adress": "105043, г. Москва, 7-я Парковая,  дом  1-а",
      "okryg": "Восточный административный округ",
      "rayon": "район Измайлово",
      "org_prav_forma": "Государственное",
      "podchinenie": "Восточное окружное управление образования",
      "tip_ychregdenia": "Общеобразовательное учреждение",
      "vid_ychregdenia": "Центр образования",
      "telefon": "(499) 367-79-54",
      "sait": "cov1483.mskobr.ru",
      "email": "director@centr1483.ru",
      "X": "37,793722",
      "Y": "55,790653",
      "global_id": "86890284"
    }
  },
  {
    "Lat": 55.801642,
    "Lon": 37.720972,
    "Id": "83351317-e53e-4126-9963-d9087098c0e8",
    "Number": 40,
    "Cells": {
      "name":
        "Государственное бюджетное образовательное учреждение города Москвы Центр образования №1080 \"Экополис\"",
      "adress": "107392, г. Москва, ул. Знаменская, д.12/4",
      "okryg": "Восточный административный округ",
      "rayon": "район Преображенское",
      "org_prav_forma": "Государственное",
      "podchinenie": "Восточное окружное управление образования",
      "tip_ychregdenia": "Общеобразовательное учреждение",
      "vid_ychregdenia": "Центр образования",
      "telefon": "(499) 161-75-39",
      "sait": "cov1080.mskobr.ru",
      "email": "s1080@mail.ru",
      "X": "37,720972",
      "Y": "55,801642",
      "global_id": "86890285"
    }
  },
  {
    "Lat": 55.666998,
    "Lon": 37.508563,
    "Id": "326763d6-ec05-4730-a8d7-39cf387d8f74",
    "Number": 41,
    "Cells": {
      "name":
        "Государственное бюджетное образовательное учреждение города Москвы Центр образования № 1488",
      "adress": "119415  г.Москва, Ленинский проспект, д.132",
      "okryg": "Западный административный округ",
      "rayon": "район Проспект Вернадского",
      "org_prav_forma": "Государственное",
      "podchinenie": "Западное окружное управление образования",
      "tip_ychregdenia": "Общеобразовательное учреждение",
      "vid_ychregdenia": "Центр образования",
      "telefon": "432-87-62",
      "sait": "co1488.mskzapad.ru",
      "email": "co1488@mail.ru",
      "X": "37,508563",
      "Y": "55,666998",
      "global_id": "86890286"
    }
  },
  {
    "Lat": 55.903542,
    "Lon": 37.554359,
    "Id": "563decbd-d705-4491-a1d1-1cf61e1dbad7",
    "Number": 42,
    "Cells": {
      "name":
        "Государственное бюджетное образовательное учреждение города Москвы центр образования № 1490",
      "adress": "127253 г. Москва, ул. Псковская, дом 12, корпус 3",
      "okryg": "Северо-Восточный административный округ",
      "rayon": "район Лианозово",
      "org_prav_forma": "Государственное",
      "podchinenie": "Северо-Восточное окружное управление образования",
      "tip_ychregdenia": "Общеобразовательное учреждение",
      "vid_ychregdenia": "Центр образования",
      "telefon": "400-76-00",
      "sait": "co1490sv.mskobr.ru",
      "email": "co1490-svuo@yandex.ru",
      "X": "37,554359",
      "Y": "55,903542",
      "global_id": "86890290"
    }
  },
  {
    "Lat": 55.864892,
    "Lon": 37.590319,
    "Id": "2aa231eb-ff36-45b3-9413-901c904ddc57",
    "Number": 43,
    "Cells": {
      "name":
        "Государственное бюджетное образовательное учреждение города Москвы центр образования № 1491",
      "adress": "127562, город Москва, улица  Каргопольская, дом 13, корпус 2",
      "okryg": "Северо-Восточный административный округ",
      "rayon": "район Отрадное",
      "org_prav_forma": "Государственное",
      "podchinenie": "Северо-Восточное окружное управление образования",
      "tip_ychregdenia": "Общеобразовательное учреждение",
      "vid_ychregdenia": "Центр образования",
      "telefon": "(499) 903-77-32",
      "sait": "co1491sv.mskobr.ru",
      "email": "sch971@yandex.ru",
      "X": "37,590319",
      "Y": "55,864892",
      "global_id": "86890291"
    }
  },
  {
    "Lat": 55.824112,
    "Lon": 37.600276,
    "Id": "79c0cedb-ce71-4673-b0a4-b8237b65b98e",
    "Number": 44,
    "Cells": {
      "name":
        "Государственное бюджетное образовательное учреждение города Москвы центр образования № 1494",
      "adress": "127427, город  Москва, улица Ботаническая, дом 9А",
      "okryg": "Северо-Восточный административный округ",
      "rayon": "район Марфино",
      "org_prav_forma": "Государственное",
      "podchinenie": "Северо-Восточное окружное управление образования",
      "tip_ychregdenia": "Общеобразовательное учреждение",
      "vid_ychregdenia": "Центр образования",
      "telefon": "(499) 975-06-08; (499) 975-06-09",
      "sait": "co1494sv.mskobr.ru/",
      "email": "School_247@bk.ru",
      "X": "37,600276",
      "Y": "55,824112",
      "global_id": "86890292"
    }
  },
  {
    "Lat": 55.694407,
    "Lon": 37.50694,
    "Id": "0663b99b-9cb8-4cf3-acdf-8112f2b5ab3f",
    "Number": 45,
    "Cells": {
      "name":
        "Государственное бюджетное образовательное учреждение города Москвы Центр образования №1498",
      "adress": "119 607 г.Москва, Мичуринский проспект, д. 23",
      "okryg": "Западный административный округ",
      "rayon": "район Раменки",
      "org_prav_forma": "Государственное",
      "podchinenie": "Западное окружное управление образования",
      "tip_ychregdenia": "Общеобразовательное учреждение",
      "vid_ychregdenia": "Центр образования",
      "telefon": "932-75-22",
      "sait": "cog1498.mskobr.ru",
      "email": "1498@mosintschool.ru",
      "X": "37,50694",
      "Y": "55,694407",
      "global_id": "86890298"
    }
  },
  {
    "Lat": 55.74121,
    "Lon": 37.66816,
    "Id": "a4b9e727-6157-45b7-955a-22c9ed6048ec",
    "Number": 46,
    "Cells": {
      "name":
        "Государственное бюджетное образовательное учреждение города Москвы Центр образования № 465",
      "adress": "109147 г.Москва, Б.Факельный пер., д.23, стр.1-1А",
      "okryg": "Центральный административный округ",
      "rayon": "Таганский район",
      "org_prav_forma": "Государственное",
      "podchinenie": "Центральное окружное управление образования",
      "tip_ychregdenia": "Общеобразовательное учреждение",
      "vid_ychregdenia": "Центр образования",
      "telefon": "911-35-26",
      "sait": "coc465.mskobr.ru",
      "email": "465sch@rambler.ru",
      "X": "37,66816",
      "Y": "55,74121",
      "global_id": "86890299"
    }
  },
  {
    "Lat": 55.566116,
    "Lon": 37.582205,
    "Id": "a6f8d992-ac12-4349-8b24-4a718a04531a",
    "Number": 47,
    "Cells": {
      "name":
        "Государственное бюджетное образовательное учреждение города Москвы Центр образования № 2006",
      "adress": "117216, г.Москва, ул. Грина, дом 18, корпус 3, строение 1",
      "okryg": "Юго-Западный административный округ",
      "rayon": "район Северное Бутово",
      "org_prav_forma": "Государственное",
      "podchinenie": "Юго-Западное окружное управление образования",
      "tip_ychregdenia": "Общеобразовательное учреждение",
      "vid_ychregdenia": "Центр образования",
      "telefon": "714-86-63",
      "sait": "http://couz2006.mskobr.ru/",
      "email": "info@school2006.ru",
      "X": "37,582205",
      "Y": "55,566116",
      "global_id": "86890301"
    }
  },
  {
    "Lat": 55.871016,
    "Lon": 37.552408,
    "Id": "4712a38e-757b-4590-a523-02d9e2e29662",
    "Number": 48,
    "Cells": {
      "name":
        "Государственное бюджетное образовательное учреждение города Москвы центр образования  № 656 имени А.С. Макаренко",
      "adress": "127474, г. Москва, Бескудниковский бульвар, дом 29",
      "okryg": "Северный административный округ",
      "rayon": "Бескудниковский район",
      "org_prav_forma": "Государственное",
      "podchinenie": "Северное окружное управление образования",
      "tip_ychregdenia": "Общеобразовательное учреждение",
      "vid_ychregdenia": "Центр образования",
      "telefon": "488-04-12",
      "sait": "cos656.mskobr.ru",
      "email": "school656@mail.ru",
      "X": "37,552408",
      "Y": "55,871016",
      "global_id": "86890304"
    }
  },
  {
    "Lat": 55.86729,
    "Lon": 37.529526,
    "Id": "e41d06eb-caa9-4081-9319-d84e9c8ef8ff",
    "Number": 49,
    "Cells": {
      "name":
        "Государственное бюджетное образовательное учреждение города Москвы центр образования № 1884",
      "adress": "\"127486,  г. Москва, ул. Дегунинская, дом 17 \"\"А\"\"\"",
      "okryg": "Северный административный округ",
      "rayon": "район Западное Дегунино",
      "org_prav_forma": "Государственное",
      "podchinenie": "Северное окружное управление образования",
      "tip_ychregdenia": "Общеобразовательное учреждение",
      "vid_ychregdenia": "Центр образования",
      "telefon": "(499) 905-48-83",
      "sait": "cos1884.mskobr.ru",
      "email": "school1884@rambler.ru",
      "X": "37,529526",
      "Y": "55,86729",
      "global_id": "86890308"
    }
  },
  {
    "Lat": 55.673647,
    "Lon": 37.531334,
    "Id": "4a96eea5-2af3-4292-a629-48316c5576d2",
    "Number": 50,
    "Cells": {
      "name":
        "Государственное бюджетное образовательное учреждение города Москвы Центр образования № 117",
      "adress": "117393, г. Москва, ул. Академика Пилюгина, дом 18, корпус 1",
      "okryg": "Юго-Западный административный округ",
      "rayon": "Ломоносовский район",
      "org_prav_forma": "Государственное",
      "podchinenie": "Юго-Западное окружное управление образования",
      "tip_ychregdenia": "Общеобразовательное учреждение",
      "vid_ychregdenia": "Центр образования",
      "telefon": "134-70-95",
      "sait": "http://couz117.mskobr.ru",
      "email": "sch117@rambler.ru",
      "X": "37,531334",
      "Y": "55,673647",
      "global_id": "86890315"
    }
  },
  {
    "Lat": 55.521714,
    "Lon": 37.548249,
    "Id": "5a0e58ac-156b-44aa-9f06-35d690af6f90",
    "Number": 51,
    "Cells": {
      "name":
        "Государственное бюджетное образовательное учреждение города Москвы Центр образования № 1456",
      "adress": "117623, г.Москва, ул. 3-я Железногорская, дом 11А",
      "okryg": "Юго-Западный административный округ",
      "rayon": "район Южное Бутово",
      "org_prav_forma": "Государственное",
      "podchinenie": "Юго-Западное окружное управление образования",
      "tip_ychregdenia": "Общеобразовательное учреждение",
      "vid_ychregdenia": "Центр образования",
      "telefon": "712-79-98",
      "sait": null,
      "email": "center1456@mosuzedu.ru",
      "X": "37,548249",
      "Y": "55,521714",
      "global_id": "86890318"
    }
  },
  {
    "Lat": 55.658691,
    "Lon": 37.612194,
    "Id": "d165a4c2-d82b-4fd8-b383-34cc7e7ec181",
    "Number": 52,
    "Cells": {
      "name":
        "Государственное бюджетное образовательное учреждение города Москвы Центр образования № 1450",
      "adress": "117556, г. Москва, ул. Фруктовая д.9",
      "okryg": "Южный административный округ",
      "rayon": "Нагорный район",
      "org_prav_forma": "Государственное",
      "podchinenie": "Южное окружное управление образования",
      "tip_ychregdenia": "Общеобразовательное учреждение",
      "vid_ychregdenia": "Центр образования",
      "telefon": "(499) 613-22-66",
      "sait": "cou1450.mskobr.ru",
      "email": "sch1450@sinergi.ru",
      "X": "37,612194",
      "Y": "55,658691",
      "global_id": "86890336"
    }
  },
  {
    "Lat": 55.573951,
    "Lon": 37.586731,
    "Id": "28f1304b-ec51-4cd1-8275-2ffc1b07a9ba",
    "Number": 53,
    "Cells": {
      "name":
        "Государственное бюджетное образовательное учреждение города Москвы Центр образования № 1613",
      "adress": "117628, г. Москва, ул. Ратная, дом 6 Б",
      "okryg": "Юго-Западный административный округ",
      "rayon": "район Северное Бутово",
      "org_prav_forma": "Государственное",
      "podchinenie": "Юго-Западное окружное управление образования",
      "tip_ychregdenia": "Общеобразовательное учреждение",
      "vid_ychregdenia": "Центр образования",
      "telefon": "711-16-45",
      "sait": "http://couz1613.mskobr.ru/",
      "email": "sch1069@mosuzedu.ru",
      "X": "37,586731",
      "Y": "55,573951",
      "global_id": "86893828"
    }
  },
  {
    "Lat": 55.760811,
    "Lon": 37.405065,
    "Id": "93d3dbd9-68a7-4215-9aab-ab8ed5dcec65",
    "Number": 54,
    "Cells": {
      "name":
        "Государственное бюджетное образовательное учреждение города Москвы центр образования № 1130",
      "adress": "121609 г. Москва, ул. Осенняя, д.8, к.1,3",
      "okryg": "Западный административный округ",
      "rayon": "район Крылатское",
      "org_prav_forma": "Государственное",
      "podchinenie": "Западное окружное управление образования",
      "tip_ychregdenia": "Общеобразовательное учреждение",
      "vid_ychregdenia": "Центр образования",
      "telefon": "(495) 413-03-04; (495) 415-29-67",
      "sait": "sch1130.mskzapad.ru",
      "email": "sch1130@mtu-net.ru",
      "X": "37,405065",
      "Y": "55,760811",
      "global_id": "86893999"
    }
  },
  {
    "Lat": 55.704435,
    "Lon": 37.758692,
    "Id": "85fd0fe0-2854-4774-992c-ed24f710d083",
    "Number": 55,
    "Cells": {
      "name":
        "Государственное бюджетное образовательное учреждение города Москвы центр образования № 641 имени Сергея Есенина",
      "adress": "109462, г. Москва, Волгоградский проспект, д.66, корпус 4",
      "okryg": "Юго-Восточный административный округ",
      "rayon": "район Кузьминки",
      "org_prav_forma": "Государственное",
      "podchinenie": "Юго-Восточное окружное управление образования",
      "tip_ychregdenia": "Общеобразовательное учреждение",
      "vid_ychregdenia": "Центр образования",
      "telefon": "(499) 172-36-36",
      "sait": "couv641.mskobr.ru",
      "email": "sch641@inbox.ru",
      "X": "37,758692",
      "Y": "55,704435",
      "global_id": "86896797"
    }
  },
  {
    "Lat": 55.679386,
    "Lon": 37.751983,
    "Id": "178d223e-0e0a-4692-9362-658271884762",
    "Number": 56,
    "Cells": {
      "name":
        "Государственное бюджетное образовательное учреждение города Москвы средняя общеобразовательная школа № 919 имени  Маршала Советского Союза С.К.Куркоткина",
      "adress": "109386, г. Москва, ул. Краснодарская, д. 25, корп. 2",
      "okryg": "Юго-Восточный административный округ",
      "rayon": "район Люблино",
      "org_prav_forma": "Государственное",
      "podchinenie": "Юго-Восточное окружное управление образования",
      "tip_ychregdenia": "Общеобразовательное учреждение",
      "vid_ychregdenia": "Центр образования",
      "telefon": "(495) 359-52-29",
      "sait": "couv919.mskobr.ru",
      "email": "sch919@yandex.ru",
      "X": "37,751983",
      "Y": "55,679386",
      "global_id": "86899617"
    }
  },
  {
    "Lat": 55.68905,
    "Lon": 37.721859,
    "Id": "dbacd73a-15cd-4a2a-b7a9-0731800461e6",
    "Number": 57,
    "Cells": {
      "name":
        "Государственное бюджетное образовательное учреждение города Москвы центр образования № 1085",
      "adress": "109548, г. Москва, ул. Гурьянова, д. 15",
      "okryg": "Юго-Восточный административный округ",
      "rayon": "район Печатники",
      "org_prav_forma": "Государственное",
      "podchinenie": "Юго-Восточное окружное управление образования",
      "tip_ychregdenia": "Общеобразовательное учреждение",
      "vid_ychregdenia": "Центр образования",
      "telefon": "353-68-50",
      "sait": "couv1085.mskobr.ru",
      "email": "school1085@yandex.ru",
      "X": "37,721859",
      "Y": "55,68905",
      "global_id": "86899631"
    }
  },
  {
    "Lat": 55.687031,
    "Lon": 37.52965,
    "Id": "5c069764-1941-4d0c-94e9-50a1af7f2f90",
    "Number": 58,
    "Cells": {
      "name":
        "Государственное бюджетное образовательное учреждение города Москвы центр образования № 118",
      "adress": "119311, г.Москва, Ленинский проспект, д.76",
      "okryg": "Юго-Западный административный округ",
      "rayon": "Ломоносовский район",
      "org_prav_forma": "Государственное",
      "podchinenie": "Юго-Западное окружное управление образования",
      "tip_ychregdenia": "Общеобразовательное учреждение",
      "vid_ychregdenia": "Центр образования",
      "telefon": "930-40-08",
      "sait": "http://www.couz118.mskobr.ru/",
      "email": "co118@inbox.ru",
      "X": "37,52965",
      "Y": "55,687031",
      "global_id": "86899659"
    }
  },
  {
    "Lat": 55.647012,
    "Lon": 37.521251,
    "Id": "991270bd-eb16-4901-b581-adccf43f48c7",
    "Number": 59,
    "Cells": {
      "name":
        "Государственное бюджетное образовательное учреждение города Москвы центр образования № 170 имени А.П.Чехова",
      "adress": "\"117485, г. Москва, Профсоюзная ул., дом 96 \"Б\"",
      "okryg": "Юго-Западный административный округ",
      "rayon": "район Коньково",
      "org_prav_forma": "Государственное",
      "podchinenie": "Юго-Западное окружное управление образования",
      "tip_ychregdenia": "Общеобразовательное учреждение",
      "vid_ychregdenia": "Центр образования",
      "telefon": "335-50-77",
      "sait": "http://couz170.mskobr.ru",
      "email": "center170@mosuzedu.ru",
      "X": "37,521251",
      "Y": "55,647012",
      "global_id": "86899665"
    }
  },
  {
    "Lat": 55.71165,
    "Lon": 37.736363,
    "Id": "c32d0811-f963-4665-9d67-de2241ec6e96",
    "Number": 60,
    "Cells": {
      "name":
        "Государственное бюджетное образовательное учреждение города Москвы центр образования № 1403",
      "adress": "109125,  г.Москва 1-й Саратовский пр-д, д. 5",
      "okryg": "Юго-Восточный административный округ",
      "rayon": "район Текстильщики",
      "org_prav_forma": "Государственное",
      "podchinenie": "Юго-Восточное окружное управление образования",
      "tip_ychregdenia": "Общеобразовательное учреждение",
      "vid_ychregdenia": "Центр образования",
      "telefon": "(499) 177-74-01; (499) 177-74-11",
      "sait": "couv1403.mskobr.ru",
      "email": "co-1403@yandex.ru",
      "X": "37,736363",
      "Y": "55,71165",
      "global_id": "86899703"
    }
  },
  {
    "Lat": 55.700624,
    "Lon": 37.774774,
    "Id": "8a40d180-224f-4d84-98b8-404964bef034",
    "Number": 61,
    "Cells": {
      "name":
        "Государственное бюджетное образовательное учреждение города Москвы центр образования № 1408",
      "adress": "109443, г. Москва, Есенинский бульвар, д. 14, корп. 2",
      "okryg": "Юго-Восточный административный округ",
      "rayon": "район Кузьминки",
      "org_prav_forma": "Государственное",
      "podchinenie": "Юго-Восточное окружное управление образования",
      "tip_ychregdenia": "Общеобразовательное учреждение",
      "vid_ychregdenia": "Центр образования",
      "telefon": "(499) 742-65-71",
      "sait": "couv1408.mskobr.ru",
      "email": "school1408@bk.ru",
      "X": "37,774774",
      "Y": "55,700624",
      "global_id": "86899706"
    }
  },
  {
    "Lat": 55.671694,
    "Lon": 37.793531,
    "Id": "80c9e9dc-69f1-45d8-92c4-2fd09e163960",
    "Number": 62,
    "Cells": {
      "name":
        "Государственное бюджетное образовательное учреждение города Москвы центр образования № 1417",
      "adress": "109559, г. Москва, ул. Марьинский парк, д. 43",
      "okryg": "Юго-Восточный административный округ",
      "rayon": "район Люблино",
      "org_prav_forma": "Государственное",
      "podchinenie": "Юго-Восточное окружное управление образования",
      "tip_ychregdenia": "Общеобразовательное учреждение",
      "vid_ychregdenia": "Центр образования",
      "telefon": "659-49-98",
      "sait": "couv1417.mskobr.ru/",
      "email": "shkola1417@mail.ru",
      "X": "37,793531",
      "Y": "55,671694",
      "global_id": "86899707"
    }
  },
  {
    "Lat": 55.713492,
    "Lon": 37.753109,
    "Id": "755fa213-0ca0-4778-af52-b0120f3b2d9d",
    "Number": 63,
    "Cells": {
      "name":
        "Государственное бюджетное образовательное учреждение города Москвы центр образования № 1421",
      "adress": "109117, г. Москва, ул. Васильцовский стан, д. 4",
      "okryg": "Юго-Восточный административный округ",
      "rayon": "Рязанский район",
      "org_prav_forma": "Государственное",
      "podchinenie": "Юго-Восточное окружное управление образования",
      "tip_ychregdenia": "Общеобразовательное учреждение",
      "vid_ychregdenia": "Центр образования",
      "telefon": "(499) 501-09-18",
      "sait": "co1421uv.mskobr.ru",
      "email": "1co1421@rambler.ru",
      "X": "37,753109",
      "Y": "55,713492",
      "global_id": "86899709"
    }
  },
  {
    "Lat": 55.689566,
    "Lon": 37.728913,
    "Id": "d4413e2d-cd07-4ca3-9dcb-167db6b6405b",
    "Number": 64,
    "Cells": {
      "name":
        "Государственное бюджетное образовательное учреждение города Москвы центр образования № 1422",
      "adress": "109548, г. Москва, ул. Шоссейная, д. 7",
      "okryg": "Юго-Восточный административный округ",
      "rayon": "район Печатники",
      "org_prav_forma": "Государственное",
      "podchinenie": "Юго-Восточное окружное управление образования",
      "tip_ychregdenia": "Общеобразовательное учреждение",
      "vid_ychregdenia": "Центр образования",
      "telefon": "(499) 746-46-38",
      "sait": "couv1422.mskobr.ru",
      "email": "centr1422@yandex.ru",
      "X": "37,728913",
      "Y": "55,689566",
      "global_id": "86899715"
    }
  },
  {
    "Lat": 55.683927,
    "Lon": 37.847861,
    "Id": "f151a058-46fa-4afe-8737-537ae6a1836b",
    "Number": 65,
    "Cells": {
      "name":
        "Государственное бюджетное образовательное учреждение города Москвы центр образования № 1439",
      "adress": "109431, г. Москва, Жулебинский бульвар, дом 38",
      "okryg": "Юго-Восточный административный округ",
      "rayon": "район Выхино-Жулебино",
      "org_prav_forma": "Государственное",
      "podchinenie": "Юго-Восточное окружное управление образования",
      "tip_ychregdenia": "Общеобразовательное учреждение",
      "vid_ychregdenia": "Центр образования",
      "telefon": "704-08-37",
      "sait": "couv1439.mskobr.ru",
      "email": "school1439@mail.ru",
      "X": "37,847861",
      "Y": "55,683927",
      "global_id": "86899717"
    }
  },
  {
    "Lat": 55.702201,
    "Lon": 37.754103,
    "Id": "47279eda-bf6a-4b55-8594-f7906d3bcada",
    "Number": 66,
    "Cells": {
      "name":
        "Государственное бюджетное образовательное учреждение города Москвы центр образования № 1469",
      "adress": "109462, г. Москва, ул. Юных Ленинцев, д. 45, корп. 2",
      "okryg": "Юго-Восточный административный округ",
      "rayon": "район Кузьминки",
      "org_prav_forma": "Государственное",
      "podchinenie": "Юго-Восточное окружное управление образования",
      "tip_ychregdenia": "Общеобразовательное учреждение",
      "vid_ychregdenia": "Центр образования",
      "telefon": "(499) 179-88-57",
      "sait": "couv1469.mskobr.ru",
      "email": "co1469@mail.ru",
      "X": "37,754103",
      "Y": "55,702201",
      "global_id": "86899719"
    }
  },
  {
    "Lat": 55.684378,
    "Lon": 37.918341,
    "Id": "b9aecda9-d351-4c04-aec0-385975604bfe",
    "Number": 67,
    "Cells": {
      "name":
        "Государственное бюджетное образовательное учреждение города Москвы центр образования № 1830",
      "adress": "111674, г. Москва, ул. 1-я Вольская, д. 5",
      "okryg": "Юго-Восточный административный округ",
      "rayon": "район Некрасовка",
      "org_prav_forma": "Государственное",
      "podchinenie": "Юго-Восточное окружное управление образования",
      "tip_ychregdenia": "Общеобразовательное учреждение",
      "vid_ychregdenia": "Центр образования",
      "telefon": "(495) 706-94-01",
      "sait": "couv1830.mskobr.ru",
      "email": "zo1830@mail.ru",
      "X": "37,918341",
      "Y": "55,684378",
      "global_id": "86899729"
    }
  },
  {
    "Lat": 55.65176,
    "Lon": 37.735698,
    "Id": "aff57768-4428-4b72-b146-6850806abfc1",
    "Number": 68,
    "Cells": {
      "name":
        "Государственное бюджетное образовательное учреждение города Москвы центр образования № 1881",
      "adress": "109369, г. Москва, ул. Перерва, дом 44",
      "okryg": "Юго-Восточный административный округ",
      "rayon": "район Марьино",
      "org_prav_forma": "Государственное",
      "podchinenie": "Юго-Восточное окружное управление образования",
      "tip_ychregdenia": "Общеобразовательное учреждение",
      "vid_ychregdenia": "Центр образования",
      "telefon": "(495) 349-21-31; (495) 349-05-30; (495) 349-14-03",
      "sait": "couv1881.mskobr.ru",
      "email": "ce1881@mail.ru",
      "X": "37,735698",
      "Y": "55,65176",
      "global_id": "86899731"
    }
  },
  {
    "Lat": 55.668719,
    "Lon": 37.747803,
    "Id": "7ccca207-0790-40b5-8c43-4575db7b4e88",
    "Number": 69,
    "Cells": {
      "name":
        "Государственное бюджетное образовательное учреждение города Москвы центр образования № 1877 \"Люблино\"",
      "adress": "109382, г. Москва, ул. Краснодонская, д. 40",
      "okryg": "Юго-Восточный административный округ",
      "rayon": "район Люблино",
      "org_prav_forma": "Государственное",
      "podchinenie": "Юго-Восточное окружное управление образования",
      "tip_ychregdenia": "Общеобразовательное учреждение",
      "vid_ychregdenia": "Центр образования",
      "telefon": "351-00-00",
      "sait": "couv1877.mskobr.ru",
      "email": "co1877@mail.ru",
      "X": "37,747803",
      "Y": "55,668719",
      "global_id": "86899732"
    }
  },
  {
    "Lat": 55.663762,
    "Lon": 37.776494,
    "Id": "44806c26-3e21-49da-aeff-c2e09281f8b2",
    "Number": 70,
    "Cells": {
      "name":
        "Государственное бюджетное образовательное учреждение города Москвы  центр образования № 1989",
      "adress": "109451, г. Москва, ул. Белореченская, д. 45, к. 2",
      "okryg": "Юго-Восточный административный округ",
      "rayon": "район Марьино",
      "org_prav_forma": "Государственное",
      "podchinenie": "Юго-Восточное окружное управление образования",
      "tip_ychregdenia": "Общеобразовательное учреждение",
      "vid_ychregdenia": "Центр образования",
      "telefon": "(495) 654-96-27; (495) 654-96-25",
      "sait": "couv1989.mskobr.ru",
      "email": "co1989@yandex.ru",
      "X": "37,776494",
      "Y": "55,663762",
      "global_id": "86899767"
    }
  },
  {
    "Lat": 55.667344,
    "Lon": 37.74821,
    "Id": "cc94fce6-3fda-4166-bda3-49204d64f704",
    "Number": 71,
    "Cells": {
      "name":
        "Государственное бюджетное образовательное учреждение города Москвы центр образования № 2010",
      "adress": "109559, г. Москва, ул. Белореченская, д. 8",
      "okryg": "Юго-Восточный административный округ",
      "rayon": "район Люблино",
      "org_prav_forma": "Государственное",
      "podchinenie": "Юго-Восточное окружное управление образования",
      "tip_ychregdenia": "Общеобразовательное учреждение",
      "vid_ychregdenia": "Центр образования",
      "telefon": "359-17-45",
      "sait": "couv2010.mskobr.ru/",
      "email": "school2010@mail.ru",
      "X": "37,74821",
      "Y": "55,667344",
      "global_id": "86899769"
    }
  },
  {
    "Lat": 55.671448,
    "Lon": 37.523572,
    "Id": "d2584c0c-202b-430d-924d-7cd02abaa395",
    "Number": 72,
    "Cells": {
      "name":
        "Государственное бюджетное образовательное учреждение города Москвы центр образования № 1311 \"Тхия\"",
      "adress": "119421, г.Москва, Ленинский проспект, дом 97, корпус 1",
      "okryg": "Юго-Западный административный округ",
      "rayon": "Обручевский район",
      "org_prav_forma": "Государственное",
      "podchinenie": "Юго-Западное окружное управление образования",
      "tip_ychregdenia": "Общеобразовательное учреждение",
      "vid_ychregdenia": "Центр образования",
      "telefon": "(499) 132-32-56",
      "sait": "http://couz1311.mskobr.ru/",
      "email": null,
      "X": "37,523572",
      "Y": "55,671448",
      "global_id": "86899795"
    }
  },
  {
    "Lat": 55.602661,
    "Lon": 37.518838,
    "Id": "2d6519a0-1685-4518-aaec-76e8c71a4af0",
    "Number": 73,
    "Cells": {
      "name":
        "Государственное бюджетное образовательное учреждение города Москвы центр образования № 1445",
      "adress": "117574, г.Москва, улица Голубинская, дом 5, корпус 4",
      "okryg": "Юго-Западный административный округ",
      "rayon": "район Ясенево",
      "org_prav_forma": "Государственное",
      "podchinenie": "Юго-Западное окружное управление образования",
      "tip_ychregdenia": "Общеобразовательное учреждение",
      "vid_ychregdenia": "Центр образования",
      "telefon": "423-38-22",
      "sait": "http://couz1445.mskobr.ru/",
      "email": "jshev@mail.ru",
      "X": "37,518838",
      "Y": "55,602661",
      "global_id": "86904006"
    }
  },
  {
    "Lat": 55.769336,
    "Lon": 37.600646,
    "Id": "c9b883c4-8f2a-420b-a643-9f3e9d8a19c3",
    "Number": 74,
    "Cells": {
      "name":
        "Государственное бюджетное образовательное учреждение города Москвы центр образования № 175",
      "adress": "127006 г.Москва, Старопименовский пер., д.5",
      "okryg": "Центральный административный округ",
      "rayon": "Тверской район",
      "org_prav_forma": "Государственное",
      "podchinenie": "Центральное окружное управление образования",
      "tip_ychregdenia": "Общеобразовательное учреждение",
      "vid_ychregdenia": "Центр образования",
      "telefon": "(495) 699-88-00; (495) 694-20-68",
      "sait": "coc175.mskobr.ru",
      "email": "school175@list.ru",
      "X": "37,600646",
      "Y": "55,769336",
      "global_id": "86904064"
    }
  },
  {
    "Lat": 55.772137,
    "Lon": 37.670134,
    "Id": "2994147c-f06b-451c-a98d-ca2796ef71c4",
    "Number": 75,
    "Cells": {
      "name":
        "Государственное бюджетное образовательное учреждение города Москвы центр образования № 345",
      "adress": "105066 г.Москва, Елоховский пр-д., д.1, стр.5",
      "okryg": "Центральный административный округ",
      "rayon": "Басманный район",
      "org_prav_forma": "Государственное",
      "podchinenie": "Центральное окружное управление образования",
      "tip_ychregdenia": "Общеобразовательное учреждение",
      "vid_ychregdenia": "Центр образования",
      "telefon": "(499) 267-66-76",
      "sait": "coc345.mskobr.ru/",
      "email": "info@school345.ru",
      "X": "37,670134",
      "Y": "55,772137",
      "global_id": "86904071"
    }
  },
  {
    "Lat": 55.743663,
    "Lon": 37.646289,
    "Id": "7512a957-954a-4f5c-9b8b-6be036d5edde",
    "Number": 76,
    "Cells": {
      "name":
        "Государственное бюджетное образовательное учреждение города Москвы центр образования № 497",
      "adress": "109240 г. Москва, 1-ый Котельнический пер., д.5",
      "okryg": "Центральный административный округ",
      "rayon": "Таганский район",
      "org_prav_forma": "Государственное",
      "podchinenie": "Центральное окружное управление образования",
      "tip_ychregdenia": "Общеобразовательное учреждение",
      "vid_ychregdenia": "Центр образования",
      "telefon": "(495) 915-30-55",
      "sait": "co497c.mskobr.ru",
      "email": "sch497@mail.ru",
      "X": "37,646289",
      "Y": "55,743663",
      "global_id": "86904082"
    }
  },
  {
    "Lat": 55.760305,
    "Lon": 37.588731,
    "Id": "c294897c-23c9-4bed-8d37-6e41c3a695e6",
    "Number": 77,
    "Cells": {
      "name":
        "Государственное бюджетное образовательное учреждение города Москвы центр образования № 1239",
      "adress": "123001 г.Москва, Вспольный пер.,д.6, стр.3",
      "okryg": "Центральный административный округ",
      "rayon": "Пресненский район",
      "org_prav_forma": "Государственное",
      "podchinenie": "Центральное окружное управление образования",
      "tip_ychregdenia": "Общеобразовательное учреждение",
      "vid_ychregdenia": "Центр образования",
      "telefon": "(495) 690-36-48; (495) 690-17-82",
      "sait": "coc1239.mskobr.ru",
      "email": "mail@1239.ru",
      "X": "37,588731",
      "Y": "55,760305",
      "global_id": "86904098"
    }
  },
  {
    "Lat": 55.773696,
    "Lon": 37.580572,
    "Id": "257f5d73-f3dd-4b00-af37-16d3bb947c51",
    "Number": 78,
    "Cells": {
      "name":
        "Государственное бюджетное образовательное учреждение города Москвы центр образования № 1240",
      "adress": "123056 г.Москва, Б.Кондратьевский пер., д.3",
      "okryg": "Центральный административный округ",
      "rayon": "Пресненский район",
      "org_prav_forma": "Государственное",
      "podchinenie": "Центральное окружное управление образования",
      "tip_ychregdenia": "Общеобразовательное учреждение",
      "vid_ychregdenia": "Центр образования",
      "telefon": "254-99-59",
      "sait": "coc1240.mskobr.ru",
      "email": "admin1240@inbox.ru",
      "X": "37,580572",
      "Y": "55,773696",
      "global_id": "86904099"
    }
  },
  {
    "Lat": 55.769404,
    "Lon": 37.619876,
    "Id": "1f64cac3-c21a-469b-9c27-c39f52063583",
    "Number": 79,
    "Cells": {
      "name":
        "Государственное бюджетное образовательное учреждение города Москвы центр образования № 1479",
      "adress": "127051 г.Москва, Большой Каретный пер., д.22, стр.6",
      "okryg": "Центральный административный округ",
      "rayon": "Тверской район",
      "org_prav_forma": "Государственное",
      "podchinenie": "Центральное окружное управление образования",
      "tip_ychregdenia": "Общеобразовательное учреждение",
      "vid_ychregdenia": "Центр образования",
      "telefon": "699-53-19",
      "sait": "coc1479.mskobr.ru",
      "email": "1276_sch@mail.ru",
      "X": "37,619876",
      "Y": "55,769404",
      "global_id": "86904114"
    }
  },
  {
    "Lat": 55.764773,
    "Lon": 37.665884,
    "Id": "1aa75ba2-737e-4479-86d1-28075ea239da",
    "Number": 80,
    "Cells": {
      "name":
        "Государственное бюджетное образовательное учреждение города Москвы центр образования № 1480",
      "adress": "105064, г.Москва, Гороховский пер., д.10, стр.1",
      "okryg": "Центральный административный округ",
      "rayon": "Басманный район",
      "org_prav_forma": "Государственное",
      "podchinenie": "Центральное окружное управление образования",
      "tip_ychregdenia": "Общеобразовательное учреждение",
      "vid_ychregdenia": "Центр образования",
      "telefon": "(499) 261-43-26",
      "sait": "coc1480.mskobr.ru",
      "email": "1480co@couo.ru",
      "X": "37,665884",
      "Y": "55,764773",
      "global_id": "86904115"
    }
  },
  {
    "Lat": 55.748903,
    "Lon": 37.651048,
    "Id": "98c42321-0b8b-4a0e-ba16-036e3bfbeaed",
    "Number": 81,
    "Cells": {
      "name":
        "Государственное бюджетное образовательное учреждение города Москвы центр образования № 1685",
      "adress": "109240 г.Москва, Берниковская набер., д.12, стр.1",
      "okryg": "Центральный административный округ",
      "rayon": "Таганский район",
      "org_prav_forma": "Государственное",
      "podchinenie": "Центральное окружное управление образования",
      "tip_ychregdenia": "Общеобразовательное учреждение",
      "vid_ychregdenia": "Центр образования",
      "telefon": "(495) 915-05-60; (495) 915-36-68",
      "sait": "co1685c.mskobr.ru",
      "email": "centre1685@mail.ru",
      "X": "37,651048",
      "Y": "55,748903",
      "global_id": "86904122"
    }
  },
  {
    "Lat": 55.903556,
    "Lon": 37.583945,
    "Id": "6cb4b0ed-2add-4d6a-9482-5c08b2962501",
    "Number": 82,
    "Cells": {
      "name":
        "Государственное бюджетное образовательное учреждение города Москвы центр образования № 166",
      "adress": "127572 г. Москва, Алтуфьевское шоссе, дом 97, корпус 3",
      "okryg": "Северо-Восточный административный округ",
      "rayon": "район Лианозово",
      "org_prav_forma": "Государственное",
      "podchinenie": "Северо-Восточное окружное управление образования",
      "tip_ychregdenia": "Общеобразовательное учреждение",
      "vid_ychregdenia": "Центр образования",
      "telefon": "(499) 200-06-15; (499) 200-52-70",
      "sait": "co166sv.mskobr.ru",
      "email": "sch166m@yandex.ru",
      "X": "37,583945",
      "Y": "55,903556",
      "global_id": "86907914"
    }
  },
  {
    "Lat": 55.851822,
    "Lon": 37.616298,
    "Id": "42c2c1d9-0997-45b8-983d-bef64d1ca1f8",
    "Number": 83,
    "Cells": {
      "name":
        "Государственное бюджетное образовательное учреждение города Москвы центр образования № 264",
      "adress": "127273 г. Москва, ул. Олонецкая, д.13",
      "okryg": "Северо-Восточный административный округ",
      "rayon": "район Отрадное",
      "org_prav_forma": "Государственное",
      "podchinenie": "Северо-Восточное окружное управление образования",
      "tip_ychregdenia": "Общеобразовательное учреждение",
      "vid_ychregdenia": "Центр образования",
      "telefon": "402-17-40",
      "sait": "co264sv.mskobr.ru",
      "email": "sch-co264@yandex.ru",
      "X": "37,616298",
      "Y": "55,851822",
      "global_id": "86907915"
    }
  },
  {
    "Lat": 55.827386,
    "Lon": 37.653065,
    "Id": "4069ca16-7aed-43f8-ab20-2a41c784bba9",
    "Number": 84,
    "Cells": {
      "name":
        "Государственное бюджетное образовательное учреждение города Москвы центр образования № 293",
      "adress": "129301, г. Москва, ул. Ярославская, д. 27",
      "okryg": "Северо-Восточный административный округ",
      "rayon": "Алексеевский район",
      "org_prav_forma": "Государственное",
      "podchinenie": "Северо-Восточное окружное управление образования",
      "tip_ychregdenia": "Общеобразовательное учреждение",
      "vid_ychregdenia": "Центр образования",
      "telefon": "(495) 683-45-70",
      "sait": "co293sv.mskobr.ru",
      "email": "Sch293@yandex.ru, vmoisto@mail.ru",
      "X": "37,653065",
      "Y": "55,827386",
      "global_id": "86907916"
    }
  },
  {
    "Lat": 55.896273,
    "Lon": 37.589413,
    "Id": "cedfd994-b872-43c5-8e83-dd36611e174e",
    "Number": 85,
    "Cells": {
      "name":
        "Государственное бюджетное образовательное учреждение города Москвы центр образования № 953",
      "adress": "127349, город Москва, Шенкурский проезд, дом 15",
      "okryg": "Северо-Восточный административный округ",
      "rayon": "район Бибирево",
      "org_prav_forma": "Государственное",
      "podchinenie": "Северо-Восточное окружное управление образования",
      "tip_ychregdenia": "Общеобразовательное учреждение",
      "vid_ychregdenia": "Центр образования",
      "telefon": "(499) 909-18-92",
      "sait": "co953sv.mskobr.ru",
      "email": "sch953@mail.ru",
      "X": "37,589413",
      "Y": "55,896273",
      "global_id": "86907917"
    }
  },
  {
    "Lat": 55.879152,
    "Lon": 37.70414,
    "Id": "ca93a9fe-eba8-4112-85e5-fc2b217b3c49",
    "Number": 86,
    "Cells": {
      "name":
        "Государственное бюджетное образовательное учреждение города Москвы центр образования № 1444",
      "adress": "129336 г.Москва, Анадырский проезд, дом 51",
      "okryg": "Северо-Восточный административный округ",
      "rayon": "Лосиноостровский район",
      "org_prav_forma": "Государственное",
      "podchinenie": "Северо-Восточное окружное управление образования",
      "tip_ychregdenia": "Общеобразовательное учреждение",
      "vid_ychregdenia": "Центр образования",
      "telefon": "474-61-11",
      "sait": "co1444sv.mskobr.ru",
      "email": "centeduc1444@yandex.ru",
      "X": "37,70414",
      "Y": "55,879152",
      "global_id": "86907919"
    }
  },
  {
    "Lat": 55.883987,
    "Lon": 37.5945,
    "Id": "ed56332d-a18f-4851-94da-cff9a9e14d57",
    "Number": 87,
    "Cells": {
      "name":
        "Государственное бюджетное образовательное учреждение города Москвы центр образования №1446",
      "adress": "127549 г. Москва, Костромская улица, дом 14, корпус 1",
      "okryg": "Северо-Восточный административный округ",
      "rayon": "Алтуфьевский район",
      "org_prav_forma": "Государственное",
      "podchinenie": "Северо-Восточное окружное управление образования",
      "tip_ychregdenia": "Общеобразовательное учреждение",
      "vid_ychregdenia": "Центр образования",
      "telefon": "(499) 902-22-27",
      "sait": "co1446sv.mskobr.ru",
      "email": "schol164@yandex.ru",
      "X": "37,5945",
      "Y": "55,883987",
      "global_id": "86907920"
    }
  },
  {
    "Lat": 55.894893,
    "Lon": 37.570176,
    "Id": "165bbbb4-60fd-43f4-b6d6-9ca954246fbf",
    "Number": 88,
    "Cells": {
      "name":
        "Государственное бюджетное образовательное учреждение города Москвы центр образования № 1449",
      "adress": "127576, город Москва, улица Угличская, дом 6 А",
      "okryg": "Северо-Восточный административный округ",
      "rayon": "район Лианозово",
      "org_prav_forma": "Государственное",
      "podchinenie": "Северо-Восточное окружное управление образования",
      "tip_ychregdenia": "Общеобразовательное учреждение",
      "vid_ychregdenia": "Центр образования",
      "telefon": "400-62-90",
      "sait": "co1449sv.mskobr.ru",
      "email": "Centredu1449@yandex.ru",
      "X": "37,570176",
      "Y": "55,894893",
      "global_id": "86907921"
    }
  },
  {
    "Lat": 55.85758,
    "Lon": 37.61286,
    "Id": "85c94e8f-5cc4-4c18-b1e8-f378d9bf64b9",
    "Number": 89,
    "Cells": {
      "name":
        "Государственное бюджетное образовательное учреждение города Москвы центр образования № 1459",
      "adress": "127273, г. Москва, ул. Отрадная, д. 11А",
      "okryg": "Северо-Восточный административный округ",
      "rayon": "район Отрадное",
      "org_prav_forma": "Государственное",
      "podchinenie": "Северо-Восточное окружное управление образования",
      "tip_ychregdenia": "Общеобразовательное учреждение",
      "vid_ychregdenia": "Центр образования",
      "telefon": "404-87-31",
      "sait": "co1459.svao.mskobr.ru/",
      "email": "mosschool959@yandex.ru",
      "X": "37,61286",
      "Y": "55,85758",
      "global_id": "86907922"
    }
  },
  {
    "Lat": 55.813175,
    "Lon": 37.655214,
    "Id": "18fe3eb6-2922-476f-b308-cea430b0b57b",
    "Number": 90,
    "Cells": {
      "name":
        "Государственное бюджетное образовательное учреждение города Москвы центр образования № 1464",
      "adress": "129626, г. Москва, улица Павла Корчагина, дом 1-а",
      "okryg": "Северо-Восточный административный округ",
      "rayon": "Алексеевский район",
      "org_prav_forma": "Государственное",
      "podchinenie": "Северо-Восточное окружное управление образования",
      "tip_ychregdenia": "Общеобразовательное учреждение",
      "vid_ychregdenia": "Центр образования",
      "telefon": "(495) 682-44-38; (495) 686-19-87",
      "sait": "co1464sv.mskobr.ru",
      "email": "co1464@yandex.ru",
      "X": "37,655214",
      "Y": "55,813175",
      "global_id": "86907923"
    }
  },
  {
    "Lat": 55.813873,
    "Lon": 37.644294,
    "Id": "c0d2ef70-0567-4aa5-9648-a0c691c8433b",
    "Number": 91,
    "Cells": {
      "name":
        "Государственное бюджетное образовательное учреждение города Москвы центр образования № 1470",
      "adress": "129164, г. Москва, ул. Маломосковская, д.7",
      "okryg": "Северо-Восточный административный округ",
      "rayon": "Алексеевский район",
      "org_prav_forma": "Государственное",
      "podchinenie": "Северо-Восточное окружное управление образования",
      "tip_ychregdenia": "Общеобразовательное учреждение",
      "vid_ychregdenia": "Центр образования",
      "telefon": "(495) 683-11-16",
      "sait": "со1470sv.mskobr.ru",
      "email": "co1470@yandex.ru",
      "X": "37,644294",
      "Y": "55,813873",
      "global_id": "86907924"
    }
  },
  {
    "Lat": 55.867096,
    "Lon": 37.635329,
    "Id": "fe7acc81-41bd-44a3-a182-94276daa2e77",
    "Number": 92,
    "Cells": {
      "name":
        "Государственное бюджетное образовательное учреждение города Москвы центр образования № 1482",
      "adress": "127081 г. Москва, ул. Заповедная, д. 12",
      "okryg": "Северо-Восточный административный округ",
      "rayon": "район Южное Медведково",
      "org_prav_forma": "Государственное",
      "podchinenie": "Северо-Восточное окружное управление образования",
      "tip_ychregdenia": "Общеобразовательное учреждение",
      "vid_ychregdenia": "Центр образования",
      "telefon":
        "(499) 477-34-59; (499) 477-54-43; (499) 477-04-60; (499) 477-62-50",
      "sait": "co1482.svao.mskobr.ru",
      "email": "co1482@yandex.ru",
      "X": "37,635329",
      "Y": "55,867096",
      "global_id": "86907925"
    }
  },
  {
    "Lat": 55.855138,
    "Lon": 37.588031,
    "Id": "0d0733d6-9ac6-4800-a28c-c61c49424533",
    "Number": 93,
    "Cells": {
      "name":
        "Государственное бюджетное образовательное учреждение города Москвы центр образования № 1486",
      "adress": "127562 г.Москва. Алтуфьевское шоссе, д.12, корпус 1",
      "okryg": "Северо-Восточный административный округ",
      "rayon": "район Отрадное",
      "org_prav_forma": "Государственное",
      "podchinenie": "Северо-Восточное окружное управление образования",
      "tip_ychregdenia": "Общеобразовательное учреждение",
      "vid_ychregdenia": "Центр образования",
      "telefon": "(499) 201-81-00; (499) 201-28-86",
      "sait": "co1486.svao.mskobr.ru",
      "email": "sch286@yandex.ru",
      "X": "37,588031",
      "Y": "55,855138",
      "global_id": "86907926"
    }
  },
  {
    "Lat": 55.835661,
    "Lon": 37.660693,
    "Id": "16fb3dd2-2794-44d3-811f-15dccf112218",
    "Number": 94,
    "Cells": {
      "name":
        "Государственное бюджетное образовательное учреждение города Москвы центр образования № 1499",
      "adress": "129128 г. Москва, ул. Ростокинская, д.3",
      "okryg": "Северо-Восточный административный округ",
      "rayon": "район Ростокино",
      "org_prav_forma": "Государственное",
      "podchinenie": "Северо-Восточное окружное управление образования",
      "tip_ychregdenia": "Общеобразовательное учреждение",
      "vid_ychregdenia": "Центр образования",
      "telefon": "(499) 181-04-47",
      "sait": "co1499sv.mskobr.ru",
      "email": "sch1499@yandex.ru",
      "X": "37,660693",
      "Y": "55,835661",
      "global_id": "86907927"
    }
  },
  {
    "Lat": 55.898723,
    "Lon": 37.611707,
    "Id": "56e1f775-e7d5-44e0-b60f-8301530e605d",
    "Number": 95,
    "Cells": {
      "name":
        "Государственное бюджетное образовательное учреждение города Москвы центр образования № 1682",
      "adress": "127543 г. Москва, ул. Белозерская, д.7",
      "okryg": "Северо-Восточный административный округ",
      "rayon": "район Бибирево",
      "org_prav_forma": "Государственное",
      "podchinenie": "Северо-Восточное окружное управление образования",
      "tip_ychregdenia": "Общеобразовательное учреждение",
      "vid_ychregdenia": "Центр образования",
      "telefon":
        "(499) 206-64-77; (499) 206-45-50; (499) 206-82-00; (499) 206-82-01",
      "sait": "co1682sv.mskobr.ru",
      "email": "Sch-1682@yandex.ru",
      "X": "37,611707",
      "Y": "55,898723",
      "global_id": "86907928"
    }
  },
  {
    "Lat": 55.900649,
    "Lon": 37.57798,
    "Id": "4f9907d9-d609-4506-8f74-e01fc249d5e3",
    "Number": 96,
    "Cells": {
      "name":
        "Государственное бюджетное образовательное учреждение города Москвы центр образования № 1430",
      "adress": "127572, г.Москва, ул.Новгородская, д.21А",
      "okryg": "Северо-Восточный административный округ",
      "rayon": "район Лианозово",
      "org_prav_forma": "Государственное",
      "podchinenie": "Северо-Восточное окружное управление образования",
      "tip_ychregdenia": "Общеобразовательное учреждение",
      "vid_ychregdenia": "Центр образования",
      "telefon": "(499) 200-14-00",
      "sait": "co1430.svao.mskobr.ru/",
      "email": "co1430@yandex.ru",
      "X": "37,57798",
      "Y": "55,900649",
      "global_id": "86907929"
    }
  },
  {
    "Lat": 55.723848,
    "Lon": 37.606723,
    "Id": "7f53c99f-35ff-423c-90b2-0b48b5493dbb",
    "Number": 97,
    "Cells": {
      "name":
        "Государственное бюджетное образовательное учреждение города Москвы Центр образования № 1496",
      "adress": "119049 г.Москва, Ленинский проспект, д.13а",
      "okryg": "Центральный административный округ",
      "rayon": "район Якиманка",
      "org_prav_forma": "Государственное",
      "podchinenie": "Центральное окружное управление образования",
      "tip_ychregdenia": "Общеобразовательное учреждение",
      "vid_ychregdenia": "Центр образования",
      "telefon": "(499) 237-29-81",
      "sait": "coc1496.mskobr.ru",
      "email": "co1496@yandex.ru",
      "X": "37,606723",
      "Y": "55,723848",
      "global_id": "86911365"
    }
  },
  {
    "Lat": 55.70481,
    "Lon": 37.46787,
    "Id": "f59fb6f7-f467-4952-a231-3ddb27d6e0cb",
    "Number": 98,
    "Cells": {
      "name":
        "Государственное бюджетное образовательное учреждение города Москвы центр образования № 1438",
      "adress": "119517 г. Москва,  Матвеевская улица, д.20, к.2",
      "okryg": "Западный административный округ",
      "rayon": "район Очаково-Матвеевское",
      "org_prav_forma": "Государственное",
      "podchinenie": "Западное окружное управление образования",
      "tip_ychregdenia": "Общеобразовательное учреждение",
      "vid_ychregdenia": "Центр образования",
      "telefon": "441-72-48",
      "sait": "co1438.mskzapad.ru",
      "email": "sc42@mail.ru",
      "X": "37,46787",
      "Y": "55,70481",
      "global_id": "86911381"
    }
  },
  {
    "Lat": 55.791843,
    "Lon": 37.598403,
    "Id": "2c0fd3b5-989f-4c32-9e8d-3ebf05d7e6f4",
    "Number": 99,
    "Cells": {
      "name":
        "Государственное бюджетное образовательное учреждение города Москвы центр образования № 204 имени А.М. Горького",
      "adress": "127055, г. Москва, ул. Тихвинская, д.39, стр.2",
      "okryg": "Центральный административный округ",
      "rayon": "Тверской район",
      "org_prav_forma": "Государственное",
      "podchinenie": "Центральное окружное управление образования",
      "tip_ychregdenia": "Общеобразовательное учреждение",
      "vid_ychregdenia": "Центр образования",
      "telefon": "(499) 972-62-41",
      "sait": "coc204.mskobr.ru/",
      "email": "co204@yandex.ru",
      "X": "37,598403",
      "Y": "55,791843",
      "global_id": "86914837"
    }
  },
  {
    "Lat": 55.737642,
    "Lon": 37.863459,
    "Id": "157d9700-659e-4851-9acf-ceabd20257c8",
    "Number": 100,
    "Cells": {
      "name":
        "Государственное бюджетное образовательное учреждение города Москвы центр образования № 1048",
      "adress": "111672, Москва, ул.Салтыковская, д.13 Б",
      "okryg": "Восточный административный округ",
      "rayon": "район Новокосино",
      "org_prav_forma": "Государственное",
      "podchinenie": "Восточное окружное управление образования",
      "tip_ychregdenia": "Общеобразовательное учреждение",
      "vid_ychregdenia": "Центр образования",
      "telefon": "(495) 701-22-00; (495) 701-22-50",
      "sait": "cov1048.mskobr.ru",
      "email": "school1048@mail.ru",
      "X": "37,863459",
      "Y": "55,737642",
      "global_id": "86914848"
    }
  }
]
