[
  {
    "global_id": 1698944,
    "Number": 1,
    "Cells": {
      "global_id": 1698944,
      "ClarificationOfWorkingHours": "обед 12:00-12:45",
      "FullName":
        "Государственное казенное учреждение Инженерная служба района Арбат",
      "ShortName": "ГКУ «ИС района Арбат»",
      "AdmArea": "Центральный административный округ",
      "District": "район Арбат",
      "Address": "улица Арбат, дом 40, строение 2-3",
      "Phone": [{ "Phone": "(499) 241-39-53" }],
      "Email": [{ "Email": "arbat-gku@mail.ru" }],
      "WorkingHours": [
        { "Hours": "08:00-17:00", "DayOfWeek": "понедельник" },
        { "Hours": "08:00-17:00", "DayOfWeek": "вторник" },
        { "Hours": "08:00-17:00", "DayOfWeek": "среда" },
        { "Hours": "08:00-17:00", "DayOfWeek": "четверг" },
        { "Hours": "08:00-17:00", "DayOfWeek": "пятница" },
        { "Hours": "выходной", "DayOfWeek": "суббота" },
        { "Hours": "выходной", "DayOfWeek": "воскресенье" }
      ],
      "geoData": {
        "type": "Point",
        "coordinates": [37.587557438246, 55.748782258828]
      }
    }
  },
  {
    "global_id": 1698945,
    "Number": 2,
    "Cells": {
      "global_id": 1698945,
      "ClarificationOfWorkingHours": "обед 12:00-12:45",
      "FullName":
        "Государственное казенное учреждение «Инженерная служба Басманного района»",
      "ShortName": "ГКУ «ИС Басманного района»",
      "AdmArea": "Центральный административный округ",
      "District": "Басманный район",
      "Address": "105066, город Москва, Басманный 1-й переулок, дом 6",
      "Phone": [{ "Phone": "(495) 607-48-61" }],
      "Email": [{ "Email": "sektor-gku@yandex.ru" }],
      "WorkingHours": [
        { "Hours": "08:00-17:00", "DayOfWeek": "понедельник" },
        { "Hours": "08:00-17:00", "DayOfWeek": "вторник" },
        { "Hours": "08:00-17:00", "DayOfWeek": "среда" },
        { "Hours": "08:00-17:00", "DayOfWeek": "четверг" },
        { "Hours": "08:00-15:45", "DayOfWeek": "пятница" },
        { "Hours": "выходной", "DayOfWeek": "суббота" },
        { "Hours": "выходной", "DayOfWeek": "воскресенье" }
      ],
      "geoData": {
        "type": "Point",
        "coordinates": [37.663622078922, 55.770864968767]
      }
    }
  },
  {
    "global_id": 1698946,
    "Number": 3,
    "Cells": {
      "global_id": 1698946,
      "ClarificationOfWorkingHours": "обед 12:00-12:45",
      "FullName":
        "Государственное казенное учреждение «Инженерная служба района Замоскворечье»",
      "ShortName": "ГКУ «ИС района Замоскворечье»",
      "AdmArea": "Центральный административный округ",
      "District": "район Замоскворечье",
      "Address": "115035. г. Москва, Пятницкая ул., д.18",
      "Phone": [{ "Phone": "(495) 953-11-26" }],
      "Email": [{ "Email": "uo_sektor@mail.ru" }],
      "WorkingHours": [
        { "Hours": "08:00-17:00", "DayOfWeek": "понедельник" },
        { "Hours": "08:00-17:00", "DayOfWeek": "вторник" },
        { "Hours": "08:00-17:00", "DayOfWeek": "среда" },
        { "Hours": "08:00-17:00", "DayOfWeek": "четверг" },
        { "Hours": "08:00-15:45", "DayOfWeek": "пятница" },
        { "Hours": "выходной", "DayOfWeek": "суббота" },
        { "Hours": "выходной", "DayOfWeek": "воскресенье" }
      ],
      "geoData": {
        "type": "Point",
        "coordinates": [37.638899808545, 55.734524574868]
      }
    }
  },
  {
    "global_id": 1698947,
    "Number": 4,
    "Cells": {
      "global_id": 1698947,
      "ClarificationOfWorkingHours": "обед 12:00-12:45",
      "FullName":
        "Государственное казенное учреждение «Инженерная служба Красносельского района»",
      "ShortName": "ГКУ «ИС Красносельского района»",
      "AdmArea": "Центральный административный округ",
      "District": "Красносельский район",
      "Address": "107140, г. Москва, Русаковская ул., д.5",
      "Phone": [{ "Phone": "(499) 264-04-52" }],
      "Email": [{ "Email": "gkuis.krasnoselsky2014@yandex.ru" }],
      "WorkingHours": [
        { "Hours": "08:00-17:00", "DayOfWeek": "понедельник" },
        { "Hours": "08:00-17:00", "DayOfWeek": "вторник" },
        { "Hours": "08:00-17:00", "DayOfWeek": "среда" },
        { "Hours": "08:00-17:00", "DayOfWeek": "четверг" },
        { "Hours": "08:00-15:45", "DayOfWeek": "пятница" },
        { "Hours": "выходной", "DayOfWeek": "суббота" },
        { "Hours": "выходной", "DayOfWeek": "воскресенье" }
      ],
      "geoData": {
        "type": "Point",
        "coordinates": [37.669541453884, 55.782614286665]
      }
    }
  },
  {
    "global_id": 1698948,
    "Number": 5,
    "Cells": {
      "global_id": 1698948,
      "ClarificationOfWorkingHours": "обед 12:00-12:45",
      "FullName":
        "Государственное казенное учреждение Инженерная служба Мещанского района",
      "ShortName": "ГКУ «ИС Мещанского района»",
      "AdmArea": "Центральный административный округ",
      "District": "Мещанский район",
      "Address": "129090, г. Москва, Ботанический переулок д.7",
      "Phone": [{ "Phone": "(495) 680-33-86" }],
      "Email": [{ "Email": "gyis@inbox.ru" }],
      "WorkingHours": [
        { "Hours": "08:00-17:00", "DayOfWeek": "понедельник" },
        { "Hours": "08:00-17:00", "DayOfWeek": "вторник" },
        { "Hours": "08:00-17:00", "DayOfWeek": "среда" },
        { "Hours": "08:00-17:00", "DayOfWeek": "четверг" },
        { "Hours": "08:00-17:00", "DayOfWeek": "пятница" },
        { "Hours": "выходной", "DayOfWeek": "суббота" },
        { "Hours": "выходной", "DayOfWeek": "воскресенье" }
      ],
      "geoData": {
        "type": "Point",
        "coordinates": [37.637818767572, 55.77833689487]
      }
    }
  },
  {
    "global_id": 1698949,
    "Number": 6,
    "Cells": {
      "global_id": 1698949,
      "ClarificationOfWorkingHours": "обед 12:00-12:45",
      "FullName":
        "Государственное казенное учреждение «Инженерная служба Пресненского района»",
      "ShortName": "ГКУ «ИС Пресненского района»",
      "AdmArea": "Центральный административный округ",
      "District": "Пресненский район",
      "Address": "123022,  г. Москва, Ул. Красная Пресня, д.26, стр.1",
      "Phone": [{ "Phone": "(495) 605-33-91" }],
      "Email": [{ "Email": "quisp2007@yandex.ru" }],
      "WorkingHours": [
        { "Hours": "08:00-17:00", "DayOfWeek": "понедельник" },
        { "Hours": "08:00-17:00", "DayOfWeek": "вторник" },
        { "Hours": "08:00-17:00", "DayOfWeek": "среда" },
        { "Hours": "08:00-17:00", "DayOfWeek": "четверг" },
        { "Hours": "08:00-17:00", "DayOfWeek": "пятница" },
        { "Hours": "выходной", "DayOfWeek": "суббота" },
        { "Hours": "выходной", "DayOfWeek": "воскресенье" }
      ],
      "geoData": {
        "type": "Point",
        "coordinates": [37.569166022429, 55.762487506847]
      }
    }
  },
  {
    "global_id": 1698950,
    "Number": 7,
    "Cells": {
      "global_id": 1698950,
      "ClarificationOfWorkingHours": "обед 12:00-12:45",
      "FullName":
        "Государственное казенное учреждение «Инженерная служба Таганского района»",
      "ShortName": "ГКУ «ИС Таганского района»",
      "AdmArea": "Центральный административный округ",
      "District": "Таганский район",
      "Address": "109044, г. Москва, 2-я Дубровская ул., дом 4",
      "Phone": [{ "Phone": "(495) 911-98-99" }],
      "Email": [{ "Email": "gkuis-taganka@yandex.ru" }],
      "WorkingHours": [
        { "Hours": "08:00-17:00", "DayOfWeek": "понедельник" },
        { "Hours": "08:00-17:00", "DayOfWeek": "вторник" },
        { "Hours": "08:00-17:00", "DayOfWeek": "среда" },
        { "Hours": "08:00-17:00", "DayOfWeek": "четверг" },
        { "Hours": "08:00-15:45", "DayOfWeek": "пятница" },
        { "Hours": "выходной", "DayOfWeek": "суббота" },
        { "Hours": "выходной", "DayOfWeek": "воскресенье" }
      ],
      "geoData": {
        "type": "Point",
        "coordinates": [37.65941040302, 55.736851371003]
      }
    }
  },
  {
    "global_id": 1698951,
    "Number": 8,
    "Cells": {
      "global_id": 1698951,
      "ClarificationOfWorkingHours": "обед 12:00-12:45",
      "FullName":
        "Государственное казенное учреждение «Инженерная служба района Хамовники»",
      "ShortName": "ГКУ «ИС района Хамовники»",
      "AdmArea": "Центральный административный округ",
      "District": "район Хамовники",
      "Address": "119048,  г. Москва,  3-я Фрунзенская ул., д.19",
      "Phone": [{ "Phone": "(495) 242-52-04" }],
      "Email": [{ "Email": "gy-hamovniki@mail.ru" }],
      "WorkingHours": [
        { "Hours": "08:00-17:00", "DayOfWeek": "понедельник" },
        { "Hours": "08:00-17:00", "DayOfWeek": "вторник" },
        { "Hours": "08:00-17:00", "DayOfWeek": "среда" },
        { "Hours": "08:00-17:00", "DayOfWeek": "четверг" },
        { "Hours": "08:00-15:45", "DayOfWeek": "пятница" },
        { "Hours": "выходной", "DayOfWeek": "суббота" },
        { "Hours": "выходной", "DayOfWeek": "воскресенье" }
      ],
      "geoData": {
        "type": "Point",
        "coordinates": [37.571962505583, 55.723382847151]
      }
    }
  },
  {
    "global_id": 1698952,
    "Number": 9,
    "Cells": {
      "global_id": 1698952,
      "ClarificationOfWorkingHours": "обед 12:00-12:45",
      "FullName":
        "Государственное казенное учреждение «Инженерная служба района Якиманка»",
      "ShortName": "ГКУ «ИС района Якиманка»",
      "AdmArea": "Центральный административный округ",
      "District": "район Якиманка",
      "Address": "Калужская площадь, д.1, корп.1",
      "Phone": [{ "Phone": "(499) 230-14-49" }],
      "Email": [{ "Email": "Guis_yakimanka@mail.ru" }],
      "WorkingHours": [
        { "Hours": "08:00-17:00", "DayOfWeek": "понедельник" },
        { "Hours": "08:00-17:00", "DayOfWeek": "вторник" },
        { "Hours": "08:00-17:00", "DayOfWeek": "среда" },
        { "Hours": "08:00-17:00", "DayOfWeek": "четверг" },
        { "Hours": "08:00-15:45", "DayOfWeek": "пятница" },
        { "Hours": "выходной", "DayOfWeek": "суббота" },
        { "Hours": "выходной", "DayOfWeek": "воскресенье" }
      ],
      "geoData": {
        "type": "Point",
        "coordinates": [37.622003623725, 55.742821632801]
      }
    }
  },
  {
    "global_id": 1698953,
    "Number": 10,
    "Cells": {
      "global_id": 1698953,
      "ClarificationOfWorkingHours": "обед 12:00-12:45",
      "FullName":
        "Государственное казенное учреждение «Инженерная служба района Аэропорт»",
      "ShortName": "ГКУ «ИС района Аэропорт»",
      "AdmArea": "Северный административный округ",
      "District": "район Аэропорт",
      "Address": "г. Москва, ул. Часовая, д. 7, корп. 1",
      "Phone": [{ "Phone": "(499) 155-88-55" }],
      "Email": [{ "Email": "guis-aeroport@pnao.mos.ru" }],
      "WorkingHours": [
        { "Hours": "08:00-17:00", "DayOfWeek": "понедельник" },
        { "Hours": "08:00-17:00", "DayOfWeek": "вторник" },
        { "Hours": "08:00-17:00", "DayOfWeek": "среда" },
        { "Hours": "08:00-17:00", "DayOfWeek": "четверг" },
        { "Hours": "08:00-15:45", "DayOfWeek": "пятница" },
        { "Hours": "выходной", "DayOfWeek": "суббота" },
        { "Hours": "выходной", "DayOfWeek": "воскресенье" }
      ],
      "geoData": {
        "type": "Point",
        "coordinates": [37.533109073928, 55.807508182949]
      }
    }
  }
]
